Workbook
Name period_selected: '[1]Project Planner'!$H$3

Sheet ui
A1: 1. Setting
A2: Country | B2: Uganda
A3: WB income setting | B3: =VLOOKUP(B2,dropdown!M:O,3,FALSE) -> LIC
A4: Start year - intervention scale up | B4: 2025
A5: End year - intervention scale up | B5: 2050
A7: 2. Cancer stage distribution | B7: Assumed
A8: cause | B8: Precancer | C8: Local | D8: Regional | E8: Distant | F8: Check
A9: Bladder cancer | F9: =EXACT(SUM(B9:E9),1) -> FALSE
A10: Breast cancer | F10: =EXACT(SUM(B10:E10),1) -> FALSE
A11: Cervical cancer | F11: =EXACT(SUM(B11:E11),1) -> FALSE
A12: Colon and rectum cancer | F12: =EXACT(SUM(B12:E12),1) -> FALSE
A13: Esophageal cancer | F13: =EXACT(SUM(B13:E13),1) -> FALSE
A14: Lip and oral cavity cancer | F14: =EXACT(SUM(B14:E14),1) -> FALSE
A15: Liver cancer | F15: =EXACT(SUM(B15:E15),1) -> FALSE
A16: Nasopharynx cancer | F16: =EXACT(SUM(B16:E16),1) -> FALSE
A17: Other pharynx cancer | F17: =EXACT(SUM(B17:E17),1) -> FALSE
A18: Ovarian cancer | F18: =EXACT(SUM(B18:E18),1) -> FALSE
A19: Pancreatic cancer | F19: =EXACT(SUM(B19:E19),1) -> FALSE
A20: Prostate cancer | F20: =EXACT(SUM(B20:E20),1) -> FALSE
... A24: Uterine cancer | F24: =EXACT(SUM(B24:E24),1) -> FALSE
A26: 3. Cancer prevention
B27: include?
A28: Tobacco excise tax (% final retail price) | B28: % (select)
A29: Tobacco regulations - advertising, front-of-pack labeling | B29: FALSE
A30: Tobacco mass media campaigns | B30: FALSE
A31: Alcohol excise tax (% final retail price) | B31: % (select)
A32: Alcohol regulations - advertising, sales | B32: FALSE
A33: Alcohol mass media campaigns | B33: FALSE
A35: 4. Cancer treatment | B35: User-defined
A36: Cancer type | B36: Target | C36: Baseline initiation coverage | D36: Baseline effective coverage | E36: Target initiation coverage | F36: Target effective coverage
A37: Bladder cancer | B37: FALSE | C37: {=INDEX(begin!G:G,MATCH(1, (A37=begin!A:A)*(B$3=begin!C:C),0))} -> 0.045 | D37: =C37*dropdown!G$6 -> 0.0405 | E37: 0.8 | F37: =E37*D37/C37 -> 0.72
A38: Breast cancer | B38: TRUE | C38: {=INDEX(begin!G:G,MATCH(1, (A38=begin!A:A)*(B$3=begin!C:C),0))} -> 0.036 | D38: =C38*dropdown!G$6 -> 0.0324 | E38: 0.8 | F38: =E38*dropdown!G5 -> 0.72
A39: Cervical cancer | B39: TRUE | C39: {=INDEX(begin!G:G,MATCH(1, (A39=begin!A:A)*(B$3=begin!C:C),0))} -> 0.0729 | D39: =C39*dropdown!G$6 -> 0.06561 | E39: 0.8 | F39: =E39*D39/C39 -> 0.72
A40: Colon and rectum cancer | B40: FALSE | C40: {=INDEX(begin!G:G,MATCH(1, (A40=begin!A:A)*(B$3=begin!C:C),0))} -> 0.0081 | D40: =C40*dropdown!G$6 -> 0.00729 | E40: 0.8 | F40: =E40*D40/C40 -> 0.72
A41: Esophageal cancer | B41: TRUE | C41: {=INDEX(begin!G:G,MATCH(1, (A41=begin!A:A)*(B$3=begin!C:C),0))} -> 0.045 | D41: =C41*dropdown!G$6 -> 0.0405 | E41: 0.8 | F41: =E41*D41/C41 -> 0.72
A42: Lip and oral cavity cancer | B42: FALSE | C42: {=INDEX(begin!G:G,MATCH(1, (A42=begin!A:A)*(B$3=begin!C:C),0))} -> 0.045 | D42: =C42*dropdown!G$6 -> 0.0405 | E42: 0.8 | F42: =E42*D42/C42 -> 0.72
A43: Liver cancer | B43: TRUE | C43: {=INDEX(begin!G:G,MATCH(1, (A43=begin!A:A)*(B$3=begin!C:C),0))} -> 0.045 | D43: =C43*dropdown!G$6 -> 0.0405 | E43: 0.8 | F43: =E43*D43/C43 -> 0.72
A44: Nasopharynx cancer | B44: FALSE | C44: {=INDEX(begin!G:G,MATCH(1, (A44=begin!A:A)*(B$3=begin!C:C),0))} -> 0.045 | D44: =C44*dropdown!G$6 -> 0.0405 | E44: 0.8 | F44: =E44*D44/C44 -> 0.72
A45: Other pharynx cancer | B45: FALSE | C45: {=INDEX(begin!G:G,MATCH(1, (A45=begin!A:A)*(B$3=begin!C:C),0))} -> 0.045 | D45: =C45*dropdown!G$6 -> 0.0405 | E45: 0.8 | F45: =E45*D45/C45 -> 0.72
A46: Ovarian cancer | B46: FALSE | C46: {=INDEX(begin!G:G,MATCH(1, (A46=begin!A:A)*(B$3=begin!C:C),0))} -> 0.045 | D46: =C46*dropdown!G$6 -> 0.0405 | E46: 0.8 | F46: =E46*D46/C46 -> 0.72
A47: Pancreatic cancer | B47: FALSE | C47: {=INDEX(begin!G:G,MATCH(1, (A47=begin!A:A)*(B$3=begin!C:C),0))} -> 0.045 | D47: =C47*dropdown!G$6 -> 0.0405 | E47: 0.8 | F47: =E47*D47/C47 -> 0.72
A48: Prostate cancer | B48: TRUE | C48: {=INDEX(begin!G:G,MATCH(1, (A48=begin!A:A)*(B$3=begin!C:C),0))} -> 0.045 | D48: =C48*dropdown!G$6 -> 0.0405 | E48: 0.8 | F48: =E48*D48/C48 -> 0.72
A49: Stomach cancer | B49: FALSE | C49: {=INDEX(begin!G:G,MATCH(1, (A49=begin!A:A)*(B$3=begin!C:C),0))} -> 0.045 | D49: =C49*dropdown!G$6 -> 0.0405 | E49: 0.8 | F49: =E49*D49/C49 -> 0.72
A50: Thyroid cancer | B50: FALSE | C50: {=INDEX(begin!G:G,MATCH(1, (A50=begin!A:A)*(B$3=begin!C:C),0))} -> 0.045 | D50: =C50*dropdown!G$6 -> 0.0405 | E50: 0.8 | F50: =E50*D50/C50 -> 0.72
... A52: Uterine cancer | B52: FALSE | C52: {=INDEX(begin!G:G,MATCH(1, (A52=begin!A:A)*(B$3=begin!C:C),0))} -> 0.045 | D52: =C52*dropdown!G$6 -> 0.0405 | E52: 0.8 | F52: =E52*D52/C52 -> 0.72
A54: 5. Cancer palliation
B55: include? | C55: current coverage | D55: target coverage
A56: Palliative care | B56: TRUE | C56: 10 | D56: 30

Sheet RR
A1: cause | B1: tp0 | C1: tp1 | D1: tp2 | E1: tp3 | F1: cfr
A2: Bladder cancer | B2: 1 | C2: 1 | D2: 1 | E2: 1 | F2: 0.9
A3: Breast cancer | B3: 1 | C3: 1 | D3: 0.1 | E3: 0.5 | F3: 0.9
A4: Cervical cancer | B4: 0.05 | C4: 1 | D4: 0.05 | E4: 0.5 | F4: 0.9 | H4: 0.05 | I4: 1 | J4: 0.05 | K4: 0.5 | L4: 0.9
A5: Colon and rectum cancer | B5: 0.2 | C5: 1 | D5: 0.2 | E5: 0.5 | F5: 0.9
A6: Esophageal cancer | B6: 1 | C6: 1 | D6: 1 | E6: 1 | F6: 0.8
A7: Lip and oral cavity cancer | B7: 1 | C7: 1 | D7: 1 | E7: 1 | F7: 0.5
A8: Liver cancer | B8: 1 | C8: 1 | D8: 1 | E8: 1 | F8: 0.8
A9: Nasopharynx cancer | B9: 1 | C9: 1 | D9: 1 | E9: 1 | F9: 0.5
A10: Other pharynx cancer | B10: 1 | C10: 1 | D10: 1 | E10: 1 | F10: 0.5
A11: Ovarian cancer | B11: 1 | C11: 1 | D11: 1 | E11: 1 | F11: 0.9
A12: Pancreatic cancer | B12: 1 | C12: 1 | D12: 1 | E12: 1 | F12: 0.9
A13: Prostate cancer | B13: 1 | C13: 1 | D13: 0.2 | E13: 0.5 | F13: 0.9
A14: Stomach cancer | B14: 1 | C14: 1 | D14: 1 | E14: 1 | F14: 0.8 | J14: tp2 | K14: tp3
A15: Thyroid cancer | B15: 1 | C15: 1 | D15: 1 | E15: 1 | F15: 0.9 | J15: 0.2 | K15: 0.5
A16: Tracheal, bronchus, and lung cancer | B16: 1 | C16: 1 | D16: 0.5 | E16: 0.9 | F16: 0.9
A17: Uterine cancer | B17: 1 | C17: 1 | D17: 1 | E17: 1 | F17: 0.5

Sheet stg_dist
A1: cause | B1: Precancer | C1: Local | D1: Regional | E1: Distant | F1: Total
A2: Bladder cancer | B2: 0 | C2: 1 | D2: 0 | E2: 0 | F2: =SUM(B2:E2) -> 1
A3: Breast cancer | B3: 0 | C3: 0.5569338 | D3: 0.2467863 | E3: 0.1962798 | F3: =SUM(B3:E3) -> 0.9999999
A4: Cervical cancer | B4: 0.9 | C4: =49.50869% * (1-$B4) -> 0.04950869 | D4: =34.54271%*(1-$B4) -> 0.03454271 | E4: =15.948602%*(1-$B4) -> 0.015948602 | F4: =SUM(B4:E4) -> 1
A5: Colon and rectum cancer | B5: 0.5 | C5: =37.69154%*(1-B5) -> 0.1884577 | D5: =40.03997%*(1-$B5) -> 0.20019985 | E5: =22.268488%*(1-B5) -> 0.11134244 | F5: =SUM(B5:E5) -> 0.99999999
A6: Esophageal cancer | B6: 0 | C6: 1 | D6: 0 | E6: 0 | F6: =SUM(B6:E6) -> 1
A7: Lip and oral cavity cancer | B7: 0 | C7: 1 | D7: 0 | E7: 0 | F7: =SUM(B7:E7) -> 1
A8: Liver cancer | B8: 0 | C8: 1 | D8: 0 | E8: 0 | F8: =SUM(B8:E8) -> 1
A9: Nasopharynx cancer | B9: 0 | C9: 1 | D9: 0 | E9: 0 | F9: =SUM(B9:E9) -> 1
A10: Other pharynx cancer | B10: 0 | C10: 1 | D10: 0 | E10: 0 | F10: =SUM(B10:E10) -> 1
A11: Ovarian cancer | B11: 0 | C11: 1 | D11: 0 | E11: 0 | F11: =SUM(B11:E11) -> 1
A12: Pancreatic cancer | B12: 0 | C12: 1 | D12: 0 | E12: 0 | F12: =SUM(B12:E12) -> 1
A13: Prostate cancer | B13: 0 | C13: 0.7455931 | D13: 0.1587829 | E13: =1-(C13+D13) -> 0.095624 | F13: =SUM(B13:E13) -> 1
A14: Stomach cancer | B14: 0 | C14: 1 | D14: 0 | E14: 0 | F14: =SUM(B14:E14) -> 1
A15: Thyroid cancer | B15: 0 | C15: 1 | D15: 0 | E15: 0 | F15: =SUM(B15:E15) -> 1
A16: Tracheal, bronchus, and lung cancer | B16: 0 | C16: 0.2671015 | D16: 0.2118995 | E16: 0.52099905 | F16: =SUM(B16:E16) -> 1.0000001
A17: Uterine cancer | B17: 0 | C17: 1 | D17: 0 | E17: 0 | F17: =SUM(B17:E17) -> 1

Sheet all_inputs
A1: cause | B1: category | C1: target_tp | D1: tag | E1: intervention | F1: effect | G1: scaleup_begin | H1: scaleup_end | I1: location | J1: setting | K1: bsln_scrn | L1: bsln_diag | M1: bsln_init_ttt | N1: bsln_adh_ttt | O1: trgt_scrn | P1: trgt_diag | Q1: trgt_init_ttt | R1: trgt_adh_ttt | S1: bsln_precancer | T1: bsln_local | U1: bsln_regional | V1: bsln_distant | W1: trgt_precancer | X1: trgt_local | Y1: trgt_regional | Z1: trgt_distant | AA1: include
A2: Bladder cancer | B2: =IF(COUNTIF(dropdown!B$2:B$12,all_inputs!A2)=1,1,IF(COUNTIF(dropdown!C$2:C$4,all_inputs!A2)=1,2,IF(COUNTIF(dropdown!D$2:D$3,all_inputs!A2)=1,3,"?"))) -> 1 | C2: well-to-precancer | D2: tp0 | E2: Tobacco regulations - advertising, front-of-pack labeling | F2: 1 | G2: =ui!B$4 -> 2025 | H2: =ui!B$5 -> 2050 | I2: =ui!B$2 -> Uganda | J2: =VLOOKUP(ui!B$2,dropdown!M:O,3,FALSE) -> LIC | N2: 1 | R2: 1 | AA2: =VLOOKUP(all_inputs!E2,ui!A$29:B$33,2,FALSE) -> FALSE
A3: Bladder cancer | B3: =IF(COUNTIF(dropdown!B$2:B$12,all_inputs!A3)=1,1,IF(COUNTIF(dropdown!C$2:C$4,all_inputs!A3)=1,2,IF(COUNTIF(dropdown!D$2:D$3,all_inputs!A3)=1,3,"?"))) -> 1 | C3: well-to-local | D3: tp1 | E3: Tobacco regulations - advertising, front-of-pack labeling | F3: =IF(AND(all_inputs!E3=dropdown!Z$8, COUNTIF(dropdown!Z$9:Z$19,all_inputs!A3)=1), dropdown!U$10, 1) -> 1 | G3: =ui!B$4 -> 2025 | H3: =ui!B$5 -> 2050 | I3: China | J3: =VLOOKUP(ui!B$2,dropdown!M:O,3,FALSE) -> LIC | N3: 1 | R3: 1 | AA3: =VLOOKUP(all_inputs!E3,ui!A$29:B$33,2,FALSE) -> FALSE
A4: Bladder cancer | B4: =IF(COUNTIF(dropdown!B$2:B$12,all_inputs!A4)=1,1,IF(COUNTIF(dropdown!C$2:C$4,all_inputs!A4)=1,2,IF(COUNTIF(dropdown!D$2:D$3,all_inputs!A4)=1,3,"?"))) -> 1 | C4: precancer-to-local | D4: tp1 | E4: Tobacco regulations - advertising, front-of-pack labeling | F4: 1 | G4: =ui!B$4 -> 2025 | H4: =ui!B$5 -> 2050 | I4: China | J4: =VLOOKUP(ui!B$2,dropdown!M:O,3,FALSE) -> LIC | N4: 1 | R4: 1 | AA4: =VLOOKUP(all_inputs!E4,ui!A$29:B$33,2,FALSE) -> FALSE
A5: Bladder cancer | B5: =IF(COUNTIF(dropdown!B$2:B$12,all_inputs!A5)=1,1,IF(COUNTIF(dropdown!C$2:C$4,all_inputs!A5)=1,2,IF(COUNTIF(dropdown!D$2:D$3,all_inputs!A5)=1,3,"?"))) -> 1 | C5: local-to-regional | D5: tp2 | E5: Tobacco regulations - advertising, front-of-pack labeling | F5: =IF(AND(all_inputs!E5=dropdown!Z$8, COUNTIF(dropdown!Z$9:Z$19,all_inputs!A5)=1), dropdown!U$12, 1) -> 1 | G5: =ui!B$4 -> 2025 | H5: =ui!B$5 -> 2050 | I5: China | J5: =VLOOKUP(ui!B$2,dropdown!M:O,3,FALSE) -> LIC | N5: 1 | R5: 1 | AA5: =VLOOKUP(all_inputs!E5,ui!A$29:B$33,2,FALSE) -> FALSE
A6: Bladder cancer | B6: =IF(COUNTIF(dropdown!B$2:B$12,all_inputs!A6)=1,1,IF(COUNTIF(dropdown!C$2:C$4,all_inputs!A6)=1,2,IF(COUNTIF(dropdown!D$2:D$3,all_inputs!A6)=1,3,"?"))) -> 1 | C6: regional-to-distant | D6: tp3 | E6: Tobacco regulations - advertising, front-of-pack labeling | F6: =IF(AND(all_inputs!E6=dropdown!Z$8, COUNTIF(dropdown!Z$9:Z$19,all_inputs!A6)=1), dropdown!U$13, 1) -> 1 | G6: =ui!B$4 -> 2025 | H6: =ui!B$5 -> 2050 | I6: China | J6: =VLOOKUP(ui!B$2,dropdown!M:O,3,FALSE) -> LIC | N6: 1 | R6: 1 | AA6: =VLOOKUP(all_inputs!E6,ui!A$29:B$33,2,FALSE) -> FALSE
A7: Bladder cancer | B7: =IF(COUNTIF(dropdown!B$2:B$12,all_inputs!A7)=1,1,IF(COUNTIF(dropdown!C$2:C$4,all_inputs!A7)=1,2,IF(COUNTIF(dropdown!D$2:D$3,all_inputs!A7)=1,3,"?"))) -> 1 | C7: distant-to-dead | D7: cfr | E7: Tobacco regulations - advertising, front-of-pack labeling | F7: =IF(AND(all_inputs!E7=dropdown!Z$8, COUNTIF(dropdown!Z$9:Z$19,all_inputs!A7)=1), dropdown!U$14, 1) -> 1 | G7: =ui!B$4 -> 2025 | H7: =ui!B$5 -> 2050 | I7: China | J7: =VLOOKUP(ui!B$2,dropdown!M:O,3,FALSE) -> LIC | N7: 1 | R7: 1 | AA7: =VLOOKUP(all_inputs!E7,ui!A$29:B$33,2,FALSE) -> FALSE
A8: Breast cancer | B8: =IF(COUNTIF(dropdown!B$2:B$12,all_inputs!A8)=1,1,IF(COUNTIF(dropdown!C$2:C$4,all_inputs!A8)=1,2,IF(COUNTIF(dropdown!D$2:D$3,all_inputs!A8)=1,3,"?"))) -> 2 | C8: well-to-precancer | D8: tp0 | E8: Tobacco regulations - advertising, front-of-pack labeling | F8: =IF(AND(all_inputs!E8=dropdown!Z$8, COUNTIF(dropdown!Z$9:Z$19,all_inputs!A8)=1), dropdown!U$9, 1) -> 1 | G8: =ui!B$4 -> 2025 | H8: =ui!B$5 -> 2050 | I8: China | J8: =VLOOKUP(ui!B$2,dropdown!M:O,3,FALSE) -> LIC | N8: 1 | R8: 1 | AA8: =VLOOKUP(all_inputs!E8,ui!A$29:B$33,2,FALSE) -> FALSE
A9: Breast cancer | B9: =IF(COUNTIF(dropdown!B$2:B$12,all_inputs!A9)=1,1,IF(COUNTIF(dropdown!C$2:C$4,all_inputs!A9)=1,2,IF(COUNTIF(dropdown!D$2:D$3,all_inputs!A9)=1,3,"?"))) -> 2 | C9: well-to-local | D9: tp1 | E9: Tobacco regulations - advertising, front-of-pack labeling | F9: 1 | G9: =ui!B$4 -> 2025 | H9: =ui!B$5 -> 2050 | I9: China | J9: =VLOOKUP(ui!B$2,dropdown!M:O,3,FALSE) -> LIC | N9: 1 | R9: 1 | AA9: =VLOOKUP(all_inputs!E9,ui!A$29:B$33,2,FALSE) -> FALSE
A10: Breast cancer | B10: =IF(COUNTIF(dropdown!B$2:B$12,all_inputs!A10)=1,1,IF(COUNTIF(dropdown!C$2:C$4,all_inputs!A10)=1,2,IF(COUNTIF(dropdown!D$2:D$3,all_inputs!A10)=1,3,"?"))) -> 2 | C10: precancer-to-local | D10: tp1 | E10: Tobacco regulations - advertising, front-of-pack labeling | F10: =IF(AND(all_inputs!E10=dropdown!Z$8, COUNTIF(dropdown!Z$9:Z$19,all_inputs!A10)=1), dropdown!U$11, 1) -> 1 | G10: =ui!B$4 -> 2025 | H10: =ui!B$5 -> 2050 | I10: China | J10: =VLOOKUP(ui!B$2,dropdown!M:O,3,FALSE) -> LIC | N10: 1 | R10: 1 | AA10: =VLOOKUP(all_inputs!E10,ui!A$29:B$33,2,FALSE) -> FALSE
A11: Breast cancer | B11: =IF(COUNTIF(dropdown!B$2:B$12,all_inputs!A11)=1,1,IF(COUNTIF(dropdown!C$2:C$4,all_inputs!A11)=1,2,IF(COUNTIF(dropdown!D$2:D$3,all_inputs!A11)=1,3,"?"))) -> 2 | C11: local-to-regional | D11: tp2 | E11: Tobacco regulations - advertising, front-of-pack labeling | F11: =IF(AND(all_inputs!E11=dropdown!Z$8, COUNTIF(dropdown!Z$9:Z$19,all_inputs!A11)=1), dropdown!U$12, 1) -> 1 | G11: =ui!B$4 -> 2025 | H11: =ui!B$5 -> 2050 | I11: China | J11: =VLOOKUP(ui!B$2,dropdown!M:O,3,FALSE) -> LIC | N11: 1 | R11: 1 | AA11: =VLOOKUP(all_inputs!E11,ui!A$29:B$33,2,FALSE) -> FALSE
A12: Breast cancer | B12: =IF(COUNTIF(dropdown!B$2:B$12,all_inputs!A12)=1,1,IF(COUNTIF(dropdown!C$2:C$4,all_inputs!A12)=1,2,IF(COUNTIF(dropdown!D$2:D$3,all_inputs!A12)=1,3,"?"))) -> 2 | C12: regional-to-distant | D12: tp3 | E12: Tobacco regulations - advertising, front-of-pack labeling | F12: =IF(AND(all_inputs!E12=dropdown!Z$8, COUNTIF(dropdown!Z$9:Z$19,all_inputs!A12)=1), dropdown!U$13, 1) -> 1 | G12: =ui!B$4 -> 2025 | H12: =ui!B$5 -> 2050 | I12: China | J12: =VLOOKUP(ui!B$2,dropdown!M:O,3,FALSE) -> LIC | N12: 1 | R12: 1 | AA12: =VLOOKUP(all_inputs!E12,ui!A$29:B$33,2,FALSE) -> FALSE
A13: Breast cancer | B13: =IF(COUNTIF(dropdown!B$2:B$12,all_inputs!A13)=1,1,IF(COUNTIF(dropdown!C$2:C$4,all_inputs!A13)=1,2,IF(COUNTIF(dropdown!D$2:D$3,all_inputs!A13)=1,3,"?"))) -> 2 | C13: distant-to-dead | D13: cfr | E13: Tobacco regulations - advertising, front-of-pack labeling | F13: =IF(AND(all_inputs!E13=dropdown!Z$8, COUNTIF(dropdown!Z$9:Z$19,all_inputs!A13)=1), dropdown!U$14, 1) -> 1 | G13: =ui!B$4 -> 2025 | H13: =ui!B$5 -> 2050 | I13: China | J13: =VLOOKUP(ui!B$2,dropdown!M:O,3,FALSE) -> LIC | N13: 1 | R13: 1 | AA13: =VLOOKUP(all_inputs!E13,ui!A$29:B$33,2,FALSE) -> FALSE
A14: Cervical cancer | B14: =IF(COUNTIF(dropdown!B$2:B$12,all_inputs!A14)=1,1,IF(COUNTIF(dropdown!C$2:C$4,all_inputs!A14)=1,2,IF(COUNTIF(dropdown!D$2:D$3,all_inputs!A14)=1,3,"?"))) -> 3 | C14: well-to-precancer | D14: tp0 | E14: Tobacco regulations - advertising, front-of-pack labeling | F14: =IF(AND(all_inputs!E14=dropdown!Z$8, COUNTIF(dropdown!Z$9:Z$19,all_inputs!A14)=1), dropdown!U$9, 1) -> 1 | G14: =ui!B$4 -> 2025 | H14: =ui!B$5 -> 2050 | I14: China | J14: =VLOOKUP(ui!B$2,dropdown!M:O,3,FALSE) -> LIC | N14: 1 | R14: 1 | AA14: =VLOOKUP(all_inputs!E14,ui!A$29:B$33,2,FALSE) -> FALSE
A15: Cervical cancer | B15: =IF(COUNTIF(dropdown!B$2:B$12,all_inputs!A15)=1,1,IF(COUNTIF(dropdown!C$2:C$4,all_inputs!A15)=1,2,IF(COUNTIF(dropdown!D$2:D$3,all_inputs!A15)=1,3,"?"))) -> 3 | C15: well-to-local | D15: tp1 | E15: Tobacco regulations - advertising, front-of-pack labeling | F15: 1 | G15: =ui!B$4 -> 2025 | H15: =ui!B$5 -> 2050 | I15: China | J15: =VLOOKUP(ui!B$2,dropdown!M:O,3,FALSE) -> LIC | N15: 1 | R15: 1 | AA15: =VLOOKUP(all_inputs!E15,ui!A$29:B$33,2,FALSE) -> FALSE
A16: Cervical cancer | B16: =IF(COUNTIF(dropdown!B$2:B$12,all_inputs!A16)=1,1,IF(COUNTIF(dropdown!C$2:C$4,all_inputs!A16)=1,2,IF(COUNTIF(dropdown!D$2:D$3,all_inputs!A16)=1,3,"?"))) -> 3 | C16: precancer-to-local | D16: tp1 | E16: Tobacco regulations - advertising, front-of-pack labeling | F16: =IF(AND(all_inputs!E16=dropdown!Z$8, COUNTIF(dropdown!Z$9:Z$19,all_inputs!A16)=1), dropdown!U$11, 1) -> 1 | G16: =ui!B$4 -> 2025 | H16: =ui!B$5 -> 2050 | I16: China | J16: =VLOOKUP(ui!B$2,dropdown!M:O,3,FALSE) -> LIC | N16: 1 | R16: 1 | AA16: =VLOOKUP(all_inputs!E16,ui!A$29:B$33,2,FALSE) -> FALSE
A17: Cervical cancer | B17: =IF(COUNTIF(dropdown!B$2:B$12,all_inputs!A17)=1,1,IF(COUNTIF(dropdown!C$2:C$4,all_inputs!A17)=1,2,IF(COUNTIF(dropdown!D$2:D$3,all_inputs!A17)=1,3,"?"))) -> 3 | C17: local-to-regional | D17: tp2 | E17: Tobacco regulations - advertising, front-of-pack labeling | F17: =IF(AND(all_inputs!E17=dropdown!Z$8, COUNTIF(dropdown!Z$9:Z$19,all_inputs!A17)=1), dropdown!U$12, 1) -> 1 | G17: =ui!B$4 -> 2025 | H17: =ui!B$5 -> 2050 | I17: China | J17: =VLOOKUP(ui!B$2,dropdown!M:O,3,FALSE) -> LIC | N17: 1 | R17: 1 | AA17: =VLOOKUP(all_inputs!E17,ui!A$29:B$33,2,FALSE) -> FALSE
A18: Cervical cancer | B18: =IF(COUNTIF(dropdown!B$2:B$12,all_inputs!A18)=1,1,IF(COUNTIF(dropdown!C$2:C$4,all_inputs!A18)=1,2,IF(COUNTIF(dropdown!D$2:D$3,all_inputs!A18)=1,3,"?"))) -> 3 | C18: regional-to-distant | D18: tp3 | E18: Tobacco regulations - advertising, front-of-pack labeling | F18: =IF(AND(all_inputs!E18=dropdown!Z$8, COUNTIF(dropdown!Z$9:Z$19,all_inputs!A18)=1), dropdown!U$13, 1) -> 1 | G18: =ui!B$4 -> 2025 | H18: =ui!B$5 -> 2050 | I18: China | J18: =VLOOKUP(ui!B$2,dropdown!M:O,3,FALSE) -> LIC | N18: 1 | R18: 1 | AA18: =VLOOKUP(all_inputs!E18,ui!A$29:B$33,2,FALSE) -> FALSE
A19: Cervical cancer | B19: =IF(COUNTIF(dropdown!B$2:B$12,all_inputs!A19)=1,1,IF(COUNTIF(dropdown!C$2:C$4,all_inputs!A19)=1,2,IF(COUNTIF(dropdown!D$2:D$3,all_inputs!A19)=1,3,"?"))) -> 3 | C19: distant-to-dead | D19: cfr | E19: Tobacco regulations - advertising, front-of-pack labeling | F19: =IF(AND(all_inputs!E19=dropdown!Z$8, COUNTIF(dropdown!Z$9:Z$19,all_inputs!A19)=1), dropdown!U$14, 1) -> 1 | G19: =ui!B$4 -> 2025 | H19: =ui!B$5 -> 2050 | I19: China | J19: =VLOOKUP(ui!B$2,dropdown!M:O,3,FALSE) -> LIC | N19: 1 | R19: 1 | AA19: =VLOOKUP(all_inputs!E19,ui!A$29:B$33,2,FALSE) -> FALSE
A20: Colon and rectum cancer | B20: =IF(COUNTIF(dropdown!B$2:B$12,all_inputs!A20)=1,1,IF(COUNTIF(dropdown!C$2:C$4,all_inputs!A20)=1,2,IF(COUNTIF(dropdown!D$2:D$3,all_inputs!A20)=1,3,"?"))) -> 3 | C20: well-to-precancer | D20: tp0 | E20: Tobacco regulations - advertising, front-of-pack labeling | F20: =IF(AND(all_inputs!E20=dropdown!Z$8, COUNTIF(dropdown!Z$9:Z$19,all_inputs!A20)=1), dropdown!U$9, 1) -> 1 | G20: =ui!B$4 -> 2025 | H20: =ui!B$5 -> 2050 | I20: China | J20: =VLOOKUP(ui!B$2,dropdown!M:O,3,FALSE) -> LIC | N20: 1 | R20: 1 | AA20: =VLOOKUP(all_inputs!E20,ui!A$29:B$33,2,FALSE) -> FALSE
A21: Colon and rectum cancer | B21: =IF(COUNTIF(dropdown!B$2:B$12,all_inputs!A21)=1,1,IF(COUNTIF(dropdown!C$2:C$4,all_inputs!A21)=1,2,IF(COUNTIF(dropdown!D$2:D$3,all_inputs!A21)=1,3,"?"))) -> 3 | C21: well-to-local | D21: tp1 | E21: Tobacco regulations - advertising, front-of-pack labeling | F21: 1 | G21: =ui!B$4 -> 2025 | H21: =ui!B$5 -> 2050 | I21: China | J21: =VLOOKUP(ui!B$2,dropdown!M:O,3,FALSE) -> LIC | N21: 1 | R21: 1 | AA21: =VLOOKUP(all_inputs!E21,ui!A$29:B$33,2,FALSE) -> FALSE
A22: Colon and rectum cancer | B22: =IF(COUNTIF(dropdown!B$2:B$12,all_inputs!A22)=1,1,IF(COUNTIF(dropdown!C$2:C$4,all_inputs!A22)=1,2,IF(COUNTIF(dropdown!D$2:D$3,all_inputs!A22)=1,3,"?"))) -> 3 | C22: precancer-to-local | D22: tp1 | E22: Tobacco regulations - advertising, front-of-pack labeling | F22: =IF(AND(all_inputs!E22=dropdown!Z$8, COUNTIF(dropdown!Z$9:Z$19,all_inputs!A22)=1), dropdown!U$11, 1) -> 1 | G22: =ui!B$4 -> 2025 | H22: =ui!B$5 -> 2050 | I22: China | J22: =VLOOKUP(ui!B$2,dropdown!M:O,3,FALSE) -> LIC | N22: 1 | R22: 1 | AA22: =VLOOKUP(all_inputs!E22,ui!A$29:B$33,2,FALSE) -> FALSE
A23: Colon and rectum cancer | B23: =IF(COUNTIF(dropdown!B$2:B$12,all_inputs!A23)=1,1,IF(COUNTIF(dropdown!C$2:C$4,all_inputs!A23)=1,2,IF(COUNTIF(dropdown!D$2:D$3,all_inputs!A23)=1,3,"?"))) -> 3 | C23: local-to-regional | D23: tp2 | E23: Tobacco regulations - advertising, front-of-pack labeling | F23: =IF(AND(all_inputs!E23=dropdown!Z$8, COUNTIF(dropdown!Z$9:Z$19,all_inputs!A23)=1), dropdown!U$12, 1) -> 1 | G23: =ui!B$4 -> 2025 | H23: =ui!B$5 -> 2050 | I23: China | J23: =VLOOKUP(ui!B$2,dropdown!M:O,3,FALSE) -> LIC | N23: 1 | R23: 1 | AA23: =VLOOKUP(all_inputs!E23,ui!A$29:B$33,2,FALSE) -> FALSE
A24: Colon and rectum cancer | B24: =IF(COUNTIF(dropdown!B$2:B$12,all_inputs!A24)=1,1,IF(COUNTIF(dropdown!C$2:C$4,all_inputs!A24)=1,2,IF(COUNTIF(dropdown!D$2:D$3,all_inputs!A24)=1,3,"?"))) -> 3 | C24: regional-to-distant | D24: tp3 | E24: Tobacco regulations - advertising, front-of-pack labeling | F24: =IF(AND(all_inputs!E24=dropdown!Z$8, COUNTIF(dropdown!Z$9:Z$19,all_inputs!A24)=1), dropdown!U$13, 1) -> 1 | G24: =ui!B$4 -> 2025 | H24: =ui!B$5 -> 2050 | I24: China | J24: =VLOOKUP(ui!B$2,dropdown!M:O,3,FALSE) -> LIC | N24: 1 | R24: 1 | AA24: =VLOOKUP(all_inputs!E24,ui!A$29:B$33,2,FALSE) -> FALSE
A25: Colon and rectum cancer | B25: =IF(COUNTIF(dropdown!B$2:B$12,all_inputs!A25)=1,1,IF(COUNTIF(dropdown!C$2:C$4,all_inputs!A25)=1,2,IF(COUNTIF(dropdown!D$2:D$3,all_inputs!A25)=1,3,"?"))) -> 3 | C25: distant-to-dead | D25: cfr | E25: Tobacco regulations - advertising, front-of-pack labeling | F25: =IF(AND(all_inputs!E25=dropdown!Z$8, COUNTIF(dropdown!Z$9:Z$19,all_inputs!A25)=1), dropdown!U$14, 1) -> 1 | G25: =ui!B$4 -> 2025 | H25: =ui!B$5 -> 2050 | I25: China | J25: =VLOOKUP(ui!B$2,dropdown!M:O,3,FALSE) -> LIC | N25: 1 | R25: 1 | AA25: =VLOOKUP(all_inputs!E25,ui!A$29:B$33,2,FALSE) -> FALSE
A26: Esophageal cancer | B26: =IF(COUNTIF(dropdown!B$2:B$12,all_inputs!A26)=1,1,IF(COUNTIF(dropdown!C$2:C$4,all_inputs!A26)=1,2,IF(COUNTIF(dropdown!D$2:D$3,all_inputs!A26)=1,3,"?"))) -> 1 | C26: well-to-precancer | D26: tp0 | E26: Tobacco regulations - advertising, front-of-pack labeling | F26: 1 | G26: =ui!B$4 -> 2025 | H26: =ui!B$5 -> 2050 | I26: China | J26: =VLOOKUP(ui!B$2,dropdown!M:O,3,FALSE) -> LIC | N26: 1 | R26: 1 | AA26: =VLOOKUP(all_inputs!E26,ui!A$29:B$33,2,FALSE) -> FALSE
A27: Esophageal cancer | B27: =IF(COUNTIF(dropdown!B$2:B$12,all_inputs!A27)=1,1,IF(COUNTIF(dropdown!C$2:C$4,all_inputs!A27)=1,2,IF(COUNTIF(dropdown!D$2:D$3,all_inputs!A27)=1,3,"?"))) -> 1 | C27: well-to-local | D27: tp1 | E27: Tobacco regulations - advertising, front-of-pack labeling | F27: =IF(AND(all_inputs!E27=dropdown!Z$8, COUNTIF(dropdown!Z$9:Z$19,all_inputs!A27)=1), dropdown!U$10, 1) -> 1 | G27: =ui!B$4 -> 2025 | H27: =ui!B$5 -> 2050 | I27: China | J27: =VLOOKUP(ui!B$2,dropdown!M:O,3,FALSE) -> LIC | N27: 1 | R27: 1 | AA27: =VLOOKUP(all_inputs!E27,ui!A$29:B$33,2,FALSE) -> FALSE
A28: Esophageal cancer | B28: =IF(COUNTIF(dropdown!B$2:B$12,all_inputs!A28)=1,1,IF(COUNTIF(dropdown!C$2:C$4,all_inputs!A28)=1,2,IF(COUNTIF(dropdown!D$2:D$3,all_inputs!A28)=1,3,"?"))) -> 1 | C28: precancer-to-local | D28: tp1 | E28: Tobacco regulations - advertising, front-of-pack labeling | F28: 1 | G28: =ui!B$4 -> 2025 | H28: =ui!B$5 -> 2050 | I28: China | J28: =VLOOKUP(ui!B$2,dropdown!M:O,3,FALSE) -> LIC | N28: 1 | R28: 1 | AA28: =VLOOKUP(all_inputs!E28,ui!A$29:B$33,2,FALSE) -> FALSE
A29: Esophageal cancer | B29: =IF(COUNTIF(dropdown!B$2:B$12,all_inputs!A29)=1,1,IF(COUNTIF(dropdown!C$2:C$4,all_inputs!A29)=1,2,IF(COUNTIF(dropdown!D$2:D$3,all_inputs!A29)=1,3,"?"))) -> 1 | C29: local-to-regional | D29: tp2 | E29: Tobacco regulations - advertising, front-of-pack labeling | F29: =IF(AND(all_inputs!E29=dropdown!Z$8, COUNTIF(dropdown!Z$9:Z$19,all_inputs!A29)=1), dropdown!U$12, 1) -> 1 | G29: =ui!B$4 -> 2025 | H29: =ui!B$5 -> 2050 | I29: China | J29: =VLOOKUP(ui!B$2,dropdown!M:O,3,FALSE) -> LIC | N29: 1 | R29: 1 | AA29: =VLOOKUP(all_inputs!E29,ui!A$29:B$33,2,FALSE) -> FALSE
A30: Esophageal cancer | B30: =IF(COUNTIF(dropdown!B$2:B$12,all_inputs!A30)=1,1,IF(COUNTIF(dropdown!C$2:C$4,all_inputs!A30)=1,2,IF(COUNTIF(dropdown!D$2:D$3,all_inputs!A30)=1,3,"?"))) -> 1 | C30: regional-to-distant | D30: tp3 | E30: Tobacco regulations - advertising, front-of-pack labeling | F30: =IF(AND(all_inputs!E30=dropdown!Z$8, COUNTIF(dropdown!Z$9:Z$19,all_inputs!A30)=1), dropdown!U$13, 1) -> 1 | G30: =ui!B$4 -> 2025 | H30: =ui!B$5 -> 2050 | I30: China | J30: =VLOOKUP(ui!B$2,dropdown!M:O,3,FALSE) -> LIC | N30: 1 | R30: 1 | AA30: =VLOOKUP(all_inputs!E30,ui!A$29:B$33,2,FALSE) -> FALSE
A31: Esophageal cancer | B31: =IF(COUNTIF(dropdown!B$2:B$12,all_inputs!A31)=1,1,IF(COUNTIF(dropdown!C$2:C$4,all_inputs!A31)=1,2,IF(COUNTIF(dropdown!D$2:D$3,all_inputs!A31)=1,3,"?"))) -> 1 | C31: distant-to-dead | D31: cfr | E31: Tobacco regulations - advertising, front-of-pack labeling | F31: =IF(AND(all_inputs!E31=dropdown!Z$8, COUNTIF(dropdown!Z$9:Z$19,all_inputs!A31)=1), dropdown!U$14, 1) -> 1 | G31: =ui!B$4 -> 2025 | H31: =ui!B$5 -> 2050 | I31: China | J31: =VLOOKUP(ui!B$2,dropdown!M:O,3,FALSE) -> LIC | N31: 1 | R31: 1 | AA31: =VLOOKUP(all_inputs!E31,ui!A$29:B$33,2,FALSE) -> FALSE
A32: Lip and oral cavity cancer | B32: =IF(COUNTIF(dropdown!B$2:B$12,all_inputs!A32)=1,1,IF(COUNTIF(dropdown!C$2:C$4,all_inputs!A32)=1,2,IF(COUNTIF(dropdown!D$2:D$3,all_inputs!A32)=1,3,"?"))) -> 1 | C32: well-to-precancer | D32: tp0 | E32: Tobacco regulations - advertising, front-of-pack labeling | F32: 1 | G32: =ui!B$4 -> 2025 | H32: =ui!B$5 -> 2050 | I32: China | J32: =VLOOKUP(ui!B$2,dropdown!M:O,3,FALSE) -> LIC | N32: 1 | R32: 1 | AA32: =VLOOKUP(all_inputs!E32,ui!A$29:B$33,2,FALSE) -> FALSE
A33: Lip and oral cavity cancer | B33: =IF(COUNTIF(dropdown!B$2:B$12,all_inputs!A33)=1,1,IF(COUNTIF(dropdown!C$2:C$4,all_inputs!A33)=1,2,IF(COUNTIF(dropdown!D$2:D$3,all_inputs!A33)=1,3,"?"))) -> 1 | C33: well-to-local | D33: tp1 | E33: Tobacco regulations - advertising, front-of-pack labeling | F33: =IF(AND(all_inputs!E33=dropdown!Z$8, COUNTIF(dropdown!Z$9:Z$19,all_inputs!A33)=1), dropdown!U$10, 1) -> 1 | G33: =ui!B$4 -> 2025 | H33: =ui!B$5 -> 2050 | I33: China | J33: =VLOOKUP(ui!B$2,dropdown!M:O,3,FALSE) -> LIC | N33: 1 | R33: 1 | AA33: =VLOOKUP(all_inputs!E33,ui!A$29:B$33,2,FALSE) -> FALSE
A34: Lip and oral cavity cancer | B34: =IF(COUNTIF(dropdown!B$2:B$12,all_inputs!A34)=1,1,IF(COUNTIF(dropdown!C$2:C$4,all_inputs!A34)=1,2,IF(COUNTIF(dropdown!D$2:D$3,all_inputs!A34)=1,3,"?"))) -> 1 | C34: precancer-to-local | D34: tp1 | E34: Tobacco regulations - advertising, front-of-pack labeling | F34: 1 | G34: =ui!B$4 -> 2025 | H34: =ui!B$5 -> 2050 | I34: China | J34: =VLOOKUP(ui!B$2,dropdown!M:O,3,FALSE) -> LIC | N34: 1 | R34: 1 | AA34: =VLOOKUP(all_inputs!E34,ui!A$29:B$33,2,FALSE) -> FALSE
A35: Lip and oral cavity cancer | B35: =IF(COUNTIF(dropdown!B$2:B$12,all_inputs!A35)=1,1,IF(COUNTIF(dropdown!C$2:C$4,all_inputs!A35)=1,2,IF(COUNTIF(dropdown!D$2:D$3,all_inputs!A35)=1,3,"?"))) -> 1 | C35: local-to-regional | D35: tp2 | E35: Tobacco regulations - advertising, front-of-pack labeling | F35: =IF(AND(all_inputs!E35=dropdown!Z$8, COUNTIF(dropdown!Z$9:Z$19,all_inputs!A35)=1), dropdown!U$12, 1) -> 1 | G35: =ui!B$4 -> 2025 | H35: =ui!B$5 -> 2050 | I35: China | J35: =VLOOKUP(ui!B$2,dropdown!M:O,3,FALSE) -> LIC | N35: 1 | R35: 1 | AA35: =VLOOKUP(all_inputs!E35,ui!A$29:B$33,2,FALSE) -> FALSE
A36: Lip and oral cavity cancer | B36: =IF(COUNTIF(dropdown!B$2:B$12,all_inputs!A36)=1,1,IF(COUNTIF(dropdown!C$2:C$4,all_inputs!A36)=1,2,IF(COUNTIF(dropdown!D$2:D$3,all_inputs!A36)=1,3,"?"))) -> 1 | C36: regional-to-distant | D36: tp3 | E36: Tobacco regulations - advertising, front-of-pack labeling | F36: =IF(AND(all_inputs!E36=dropdown!Z$8, COUNTIF(dropdown!Z$9:Z$19,all_inputs!A36)=1), dropdown!U$13, 1) -> 1 | G36: =ui!B$4 -> 2025 | H36: =ui!B$5 -> 2050 | I36: China | J36: =VLOOKUP(ui!B$2,dropdown!M:O,3,FALSE) -> LIC | N36: 1 | R36: 1 | AA36: =VLOOKUP(all_inputs!E36,ui!A$29:B$33,2,FALSE) -> FALSE
A37: Lip and oral cavity cancer | B37: =IF(COUNTIF(dropdown!B$2:B$12,all_inputs!A37)=1,1,IF(COUNTIF(dropdown!C$2:C$4,all_inputs!A37)=1,2,IF(COUNTIF(dropdown!D$2:D$3,all_inputs!A37)=1,3,"?"))) -> 1 | C37: distant-to-dead | D37: cfr | E37: Tobacco regulations - advertising, front-of-pack labeling | F37: =IF(AND(all_inputs!E37=dropdown!Z$8, COUNTIF(dropdown!Z$9:Z$19,all_inputs!A37)=1), dropdown!U$14, 1) -> 1 | G37: =ui!B$4 -> 2025 | H37: =ui!B$5 -> 2050 | I37: China | J37: =VLOOKUP(ui!B$2,dropdown!M:O,3,FALSE) -> LIC | N37: 1 | R37: 1 | AA37: =VLOOKUP(all_inputs!E37,ui!A$29:B$33,2,FALSE) -> FALSE
A38: Liver cancer | B38: =IF(COUNTIF(dropdown!B$2:B$12,all_inputs!A38)=1,1,IF(COUNTIF(dropdown!C$2:C$4,all_inputs!A38)=1,2,IF(COUNTIF(dropdown!D$2:D$3,all_inputs!A38)=1,3,"?"))) -> 1 | C38: well-to-precancer | D38: tp0 | E38: Tobacco regulations - advertising, front-of-pack labeling | F38: 1 | G38: =ui!B$4 -> 2025 | H38: =ui!B$5 -> 2050 | I38: China | J38: =VLOOKUP(ui!B$2,dropdown!M:O,3,FALSE) -> LIC | N38: 1 | R38: 1 | AA38: =VLOOKUP(all_inputs!E38,ui!A$29:B$33,2,FALSE) -> FALSE
A39: Liver cancer | B39: =IF(COUNTIF(dropdown!B$2:B$12,all_inputs!A39)=1,1,IF(COUNTIF(dropdown!C$2:C$4,all_inputs!A39)=1,2,IF(COUNTIF(dropdown!D$2:D$3,all_inputs!A39)=1,3,"?"))) -> 1 | C39: well-to-local | D39: tp1 | E39: Tobacco regulations - advertising, front-of-pack labeling | F39: =IF(AND(all_inputs!E39=dropdown!Z$8, COUNTIF(dropdown!Z$9:Z$19,all_inputs!A39)=1), dropdown!U$10, 1) -> 1 | G39: =ui!B$4 -> 2025 | H39: =ui!B$5 -> 2050 | I39: China | J39: =VLOOKUP(ui!B$2,dropdown!M:O,3,FALSE) -> LIC | N39: 1 | R39: 1 | AA39: =VLOOKUP(all_inputs!E39,ui!A$29:B$33,2,FALSE) -> FALSE
A40: Liver cancer | B40: =IF(COUNTIF(dropdown!B$2:B$12,all_inputs!A40)=1,1,IF(COUNTIF(dropdown!C$2:C$4,all_inputs!A40)=1,2,IF(COUNTIF(dropdown!D$2:D$3,all_inputs!A40)=1,3,"?"))) -> 1 | C40: precancer-to-local | D40: tp1 | E40: Tobacco regulations - advertising, front-of-pack labeling | F40: 1 | G40: =ui!B$4 -> 2025 | H40: =ui!B$5 -> 2050 | I40: China | J40: =VLOOKUP(ui!B$2,dropdown!M:O,3,FALSE) -> LIC | N40: 1 | R40: 1 | AA40: =VLOOKUP(all_inputs!E40,ui!A$29:B$33,2,FALSE) -> FALSE
A41: Liver cancer | B41: =IF(COUNTIF(dropdown!B$2:B$12,all_inputs!A41)=1,1,IF(COUNTIF(dropdown!C$2:C$4,all_inputs!A41)=1,2,IF(COUNTIF(dropdown!D$2:D$3,all_inputs!A41)=1,3,"?"))) -> 1 | C41: local-to-regional | D41: tp2 | E41: Tobacco regulations - advertising, front-of-pack labeling | F41: =IF(AND(all_inputs!E41=dropdown!Z$8, COUNTIF(dropdown!Z$9:Z$19,all_inputs!A41)=1), dropdown!U$12, 1) -> 1 | G41: =ui!B$4 -> 2025 | H41: =ui!B$5 -> 2050 | I41: China | J41: =VLOOKUP(ui!B$2,dropdown!M:O,3,FALSE) -> LIC | N41: 1 | R41: 1 | AA41: =VLOOKUP(all_inputs!E41,ui!A$29:B$33,2,FALSE) -> FALSE
A42: Liver cancer | B42: =IF(COUNTIF(dropdown!B$2:B$12,all_inputs!A42)=1,1,IF(COUNTIF(dropdown!C$2:C$4,all_inputs!A42)=1,2,IF(COUNTIF(dropdown!D$2:D$3,all_inputs!A42)=1,3,"?"))) -> 1 | C42: regional-to-distant | D42: tp3 | E42: Tobacco regulations - advertising, front-of-pack labeling | F42: =IF(AND(all_inputs!E42=dropdown!Z$8, COUNTIF(dropdown!Z$9:Z$19,all_inputs!A42)=1), dropdown!U$13, 1) -> 1 | G42: =ui!B$4 -> 2025 | H42: =ui!B$5 -> 2050 | I42: China | J42: =VLOOKUP(ui!B$2,dropdown!M:O,3,FALSE) -> LIC | N42: 1 | R42: 1 | AA42: =VLOOKUP(all_inputs!E42,ui!A$29:B$33,2,FALSE) -> FALSE
A43: Liver cancer | B43: =IF(COUNTIF(dropdown!B$2:B$12,all_inputs!A43)=1,1,IF(COUNTIF(dropdown!C$2:C$4,all_inputs!A43)=1,2,IF(COUNTIF(dropdown!D$2:D$3,all_inputs!A43)=1,3,"?"))) -> 1 | C43: distant-to-dead | D43: cfr | E43: Tobacco regulations - advertising, front-of-pack labeling | F43: =IF(AND(all_inputs!E43=dropdown!Z$8, COUNTIF(dropdown!Z$9:Z$19,all_inputs!A43)=1), dropdown!U$14, 1) -> 1 | G43: =ui!B$4 -> 2025 | H43: =ui!B$5 -> 2050 | I43: China | J43: =VLOOKUP(ui!B$2,dropdown!M:O,3,FALSE) -> LIC | N43: 1 | R43: 1 | AA43: =VLOOKUP(all_inputs!E43,ui!A$29:B$33,2,FALSE) -> FALSE
A44: Nasopharynx cancer | B44: =IF(COUNTIF(dropdown!B$2:B$12,all_inputs!A44)=1,1,IF(COUNTIF(dropdown!C$2:C$4,all_inputs!A44)=1,2,IF(COUNTIF(dropdown!D$2:D$3,all_inputs!A44)=1,3,"?"))) -> 1 | C44: well-to-precancer | D44: tp0 | E44: Tobacco regulations - advertising, front-of-pack labeling | F44: 1 | G44: =ui!B$4 -> 2025 | H44: =ui!B$5 -> 2050 | I44: China | J44: =VLOOKUP(ui!B$2,dropdown!M:O,3,FALSE) -> LIC | N44: 1 | R44: 1 | AA44: =VLOOKUP(all_inputs!E44,ui!A$29:B$33,2,FALSE) -> FALSE
A45: Nasopharynx cancer | B45: =IF(COUNTIF(dropdown!B$2:B$12,all_inputs!A45)=1,1,IF(COUNTIF(dropdown!C$2:C$4,all_inputs!A45)=1,2,IF(COUNTIF(dropdown!D$2:D$3,all_inputs!A45)=1,3,"?"))) -> 1 | C45: well-to-local | D45: tp1 | E45: Tobacco regulations - advertising, front-of-pack labeling | F45: =IF(AND(all_inputs!E45=dropdown!Z$8, COUNTIF(dropdown!Z$9:Z$19,all_inputs!A45)=1), dropdown!U$10, 1) -> 1 | G45: =ui!B$4 -> 2025 | H45: =ui!B$5 -> 2050 | I45: China | J45: =VLOOKUP(ui!B$2,dropdown!M:O,3,FALSE) -> LIC | N45: 1 | R45: 1 | AA45: =VLOOKUP(all_inputs!E45,ui!A$29:B$33,2,FALSE) -> FALSE
A46: Nasopharynx cancer | B46: =IF(COUNTIF(dropdown!B$2:B$12,all_inputs!A46)=1,1,IF(COUNTIF(dropdown!C$2:C$4,all_inputs!A46)=1,2,IF(COUNTIF(dropdown!D$2:D$3,all_inputs!A46)=1,3,"?"))) -> 1 | C46: precancer-to-local | D46: tp1 | E46: Tobacco regulations - advertising, front-of-pack labeling | F46: 1 | G46: =ui!B$4 -> 2025 | H46: =ui!B$5 -> 2050 | I46: China | J46: =VLOOKUP(ui!B$2,dropdown!M:O,3,FALSE) -> LIC | N46: 1 | R46: 1 | AA46: =VLOOKUP(all_inputs!E46,ui!A$29:B$33,2,FALSE) -> FALSE
A47: Nasopharynx cancer | B47: =IF(COUNTIF(dropdown!B$2:B$12,all_inputs!A47)=1,1,IF(COUNTIF(dropdown!C$2:C$4,all_inputs!A47)=1,2,IF(COUNTIF(dropdown!D$2:D$3,all_inputs!A47)=1,3,"?"))) -> 1 | C47: local-to-regional | D47: tp2 | E47: Tobacco regulations - advertising, front-of-pack labeling | F47: =IF(AND(all_inputs!E47=dropdown!Z$8, COUNTIF(dropdown!Z$9:Z$19,all_inputs!A47)=1), dropdown!U$12, 1) -> 1 | G47: =ui!B$4 -> 2025 | H47: =ui!B$5 -> 2050 | I47: China | J47: =VLOOKUP(ui!B$2,dropdown!M:O,3,FALSE) -> LIC | N47: 1 | R47: 1 | AA47: =VLOOKUP(all_inputs!E47,ui!A$29:B$33,2,FALSE) -> FALSE
A48: Nasopharynx cancer | B48: =IF(COUNTIF(dropdown!B$2:B$12,all_inputs!A48)=1,1,IF(COUNTIF(dropdown!C$2:C$4,all_inputs!A48)=1,2,IF(COUNTIF(dropdown!D$2:D$3,all_inputs!A48)=1,3,"?"))) -> 1 | C48: regional-to-distant | D48: tp3 | E48: Tobacco regulations - advertising, front-of-pack labeling | F48: =IF(AND(all_inputs!E48=dropdown!Z$8, COUNTIF(dropdown!Z$9:Z$19,all_inputs!A48)=1), dropdown!U$13, 1) -> 1 | G48: =ui!B$4 -> 2025 | H48: =ui!B$5 -> 2050 | I48: China | J48: =VLOOKUP(ui!B$2,dropdown!M:O,3,FALSE) -> LIC | N48: 1 | R48: 1 | AA48: =VLOOKUP(all_inputs!E48,ui!A$29:B$33,2,FALSE) -> FALSE
A49: Nasopharynx cancer | B49: =IF(COUNTIF(dropdown!B$2:B$12,all_inputs!A49)=1,1,IF(COUNTIF(dropdown!C$2:C$4,all_inputs!A49)=1,2,IF(COUNTIF(dropdown!D$2:D$3,all_inputs!A49)=1,3,"?"))) -> 1 | C49: distant-to-dead | D49: cfr | E49: Tobacco regulations - advertising, front-of-pack labeling | F49: =IF(AND(all_inputs!E49=dropdown!Z$8, COUNTIF(dropdown!Z$9:Z$19,all_inputs!A49)=1), dropdown!U$14, 1) -> 1 | G49: =ui!B$4 -> 2025 | H49: =ui!B$5 -> 2050 | I49: China | J49: =VLOOKUP(ui!B$2,dropdown!M:O,3,FALSE) -> LIC | N49: 1 | R49: 1 | AA49: =VLOOKUP(all_inputs!E49,ui!A$29:B$33,2,FALSE) -> FALSE
A50: Other pharynx cancer | B50: =IF(COUNTIF(dropdown!B$2:B$12,all_inputs!A50)=1,1,IF(COUNTIF(dropdown!C$2:C$4,all_inputs!A50)=1,2,IF(COUNTIF(dropdown!D$2:D$3,all_inputs!A50)=1,3,"?"))) -> 1 | C50: well-to-precancer | D50: tp0 | E50: Tobacco regulations - advertising, front-of-pack labeling | F50: 1 | G50: =ui!B$4 -> 2025 | H50: =ui!B$5 -> 2050 | I50: China | J50: =VLOOKUP(ui!B$2,dropdown!M:O,3,FALSE) -> LIC | N50: 1 | R50: 1 | AA50: =VLOOKUP(all_inputs!E50,ui!A$29:B$33,2,FALSE) -> FALSE
A51: Other pharynx cancer | B51: =IF(COUNTIF(dropdown!B$2:B$12,all_inputs!A51)=1,1,IF(COUNTIF(dropdown!C$2:C$4,all_inputs!A51)=1,2,IF(COUNTIF(dropdown!D$2:D$3,all_inputs!A51)=1,3,"?"))) -> 1 | C51: well-to-local | D51: tp1 | E51: Tobacco regulations - advertising, front-of-pack labeling | F51: =IF(AND(all_inputs!E51=dropdown!Z$8, COUNTIF(dropdown!Z$9:Z$19,all_inputs!A51)=1), dropdown!U$10, 1) -> 1 | G51: =ui!B$4 -> 2025 | H51: =ui!B$5 -> 2050 | I51: China | J51: =VLOOKUP(ui!B$2,dropdown!M:O,3,FALSE) -> LIC | N51: 1 | R51: 1 | AA51: =VLOOKUP(all_inputs!E51,ui!A$29:B$33,2,FALSE) -> FALSE
A52: Other pharynx cancer | B52: =IF(COUNTIF(dropdown!B$2:B$12,all_inputs!A52)=1,1,IF(COUNTIF(dropdown!C$2:C$4,all_inputs!A52)=1,2,IF(COUNTIF(dropdown!D$2:D$3,all_inputs!A52)=1,3,"?"))) -> 1 | C52: precancer-to-local | D52: tp1 | E52: Tobacco regulations - advertising, front-of-pack labeling | F52: 1 | G52: =ui!B$4 -> 2025 | H52: =ui!B$5 -> 2050 | I52: China | J52: =VLOOKUP(ui!B$2,dropdown!M:O,3,FALSE) -> LIC | N52: 1 | R52: 1 | AA52: =VLOOKUP(all_inputs!E52,ui!A$29:B$33,2,FALSE) -> FALSE
A53: Other pharynx cancer | B53: =IF(COUNTIF(dropdown!B$2:B$12,all_inputs!A53)=1,1,IF(COUNTIF(dropdown!C$2:C$4,all_inputs!A53)=1,2,IF(COUNTIF(dropdown!D$2:D$3,all_inputs!A53)=1,3,"?"))) -> 1 | C53: local-to-regional | D53: tp2 | E53: Tobacco regulations - advertising, front-of-pack labeling | F53: =IF(AND(all_inputs!E53=dropdown!Z$8, COUNTIF(dropdown!Z$9:Z$19,all_inputs!A53)=1), dropdown!U$12, 1) -> 1 | G53: =ui!B$4 -> 2025 | H53: =ui!B$5 -> 2050 | I53: China | J53: =VLOOKUP(ui!B$2,dropdown!M:O,3,FALSE) -> LIC | N53: 1 | R53: 1 | AA53: =VLOOKUP(all_inputs!E53,ui!A$29:B$33,2,FALSE) -> FALSE
A54: Other pharynx cancer | B54: =IF(COUNTIF(dropdown!B$2:B$12,all_inputs!A54)=1,1,IF(COUNTIF(dropdown!C$2:C$4,all_inputs!A54)=1,2,IF(COUNTIF(dropdown!D$2:D$3,all_inputs!A54)=1,3,"?"))) -> 1 | C54: regional-to-distant | D54: tp3 | E54: Tobacco regulations - advertising, front-of-pack labeling | F54: =IF(AND(all_inputs!E54=dropdown!Z$8, COUNTIF(dropdown!Z$9:Z$19,all_inputs!A54)=1), dropdown!U$13, 1) -> 1 | G54: =ui!B$4 -> 2025 | H54: =ui!B$5 -> 2050 | I54: China | J54: =VLOOKUP(ui!B$2,dropdown!M:O,3,FALSE) -> LIC | N54: 1 | R54: 1 | AA54: =VLOOKUP(all_inputs!E54,ui!A$29:B$33,2,FALSE) -> FALSE
A55: Other pharynx cancer | B55: =IF(COUNTIF(dropdown!B$2:B$12,all_inputs!A55)=1,1,IF(COUNTIF(dropdown!C$2:C$4,all_inputs!A55)=1,2,IF(COUNTIF(dropdown!D$2:D$3,all_inputs!A55)=1,3,"?"))) -> 1 | C55: distant-to-dead | D55: cfr | E55: Tobacco regulations - advertising, front-of-pack labeling | F55: =IF(AND(all_inputs!E55=dropdown!Z$8, COUNTIF(dropdown!Z$9:Z$19,all_inputs!A55)=1), dropdown!U$14, 1) -> 1 | G55: =ui!B$4 -> 2025 | H55: =ui!B$5 -> 2050 | I55: China | J55: =VLOOKUP(ui!B$2,dropdown!M:O,3,FALSE) -> LIC | N55: 1 | R55: 1 | AA55: =VLOOKUP(all_inputs!E55,ui!A$29:B$33,2,FALSE) -> FALSE
A56: Ovarian cancer | B56: =IF(COUNTIF(dropdown!B$2:B$12,all_inputs!A56)=1,1,IF(COUNTIF(dropdown!C$2:C$4,all_inputs!A56)=1,2,IF(COUNTIF(dropdown!D$2:D$3,all_inputs!A56)=1,3,"?"))) -> 1 | C56: well-to-precancer | D56: tp0 | E56: Tobacco regulations - advertising, front-of-pack labeling | F56: 1 | G56: =ui!B$4 -> 2025 | H56: =ui!B$5 -> 2050 | I56: China | J56: =VLOOKUP(ui!B$2,dropdown!M:O,3,FALSE) -> LIC | N56: 1 | R56: 1 | AA56: =VLOOKUP(all_inputs!E56,ui!A$29:B$33,2,FALSE) -> FALSE
A57: Ovarian cancer | B57: =IF(COUNTIF(dropdown!B$2:B$12,all_inputs!A57)=1,1,IF(COUNTIF(dropdown!C$2:C$4,all_inputs!A57)=1,2,IF(COUNTIF(dropdown!D$2:D$3,all_inputs!A57)=1,3,"?"))) -> 1 | C57: well-to-local | D57: tp1 | E57: Tobacco regulations - advertising, front-of-pack labeling | F57: =IF(AND(all_inputs!E57=dropdown!Z$8, COUNTIF(dropdown!Z$9:Z$19,all_inputs!A57)=1), dropdown!U$10, 1) -> 1 | G57: =ui!B$4 -> 2025 | H57: =ui!B$5 -> 2050 | I57: China | J57: =VLOOKUP(ui!B$2,dropdown!M:O,3,FALSE) -> LIC | N57: 1 | R57: 1 | AA57: =VLOOKUP(all_inputs!E57,ui!A$29:B$33,2,FALSE) -> FALSE
A58: Ovarian cancer | B58: =IF(COUNTIF(dropdown!B$2:B$12,all_inputs!A58)=1,1,IF(COUNTIF(dropdown!C$2:C$4,all_inputs!A58)=1,2,IF(COUNTIF(dropdown!D$2:D$3,all_inputs!A58)=1,3,"?"))) -> 1 | C58: precancer-to-local | D58: tp1 | E58: Tobacco regulations - advertising, front-of-pack labeling | F58: 1 | G58: =ui!B$4 -> 2025 | H58: =ui!B$5 -> 2050 | I58: China | J58: =VLOOKUP(ui!B$2,dropdown!M:O,3,FALSE) -> LIC | N58: 1 | R58: 1 | AA58: =VLOOKUP(all_inputs!E58,ui!A$29:B$33,2,FALSE) -> FALSE
A59: Ovarian cancer | B59: =IF(COUNTIF(dropdown!B$2:B$12,all_inputs!A59)=1,1,IF(COUNTIF(dropdown!C$2:C$4,all_inputs!A59)=1,2,IF(COUNTIF(dropdown!D$2:D$3,all_inputs!A59)=1,3,"?"))) -> 1 | C59: local-to-regional | D59: tp2 | E59: Tobacco regulations - advertising, front-of-pack labeling | F59: =IF(AND(all_inputs!E59=dropdown!Z$8, COUNTIF(dropdown!Z$9:Z$19,all_inputs!A59)=1), dropdown!U$12, 1) -> 1 | G59: =ui!B$4 -> 2025 | H59: =ui!B$5 -> 2050 | I59: China | J59: =VLOOKUP(ui!B$2,dropdown!M:O,3,FALSE) -> LIC | N59: 1 | R59: 1 | AA59: =VLOOKUP(all_inputs!E59,ui!A$29:B$33,2,FALSE) -> FALSE
A60: Ovarian cancer | B60: =IF(COUNTIF(dropdown!B$2:B$12,all_inputs!A60)=1,1,IF(COUNTIF(dropdown!C$2:C$4,all_inputs!A60)=1,2,IF(COUNTIF(dropdown!D$2:D$3,all_inputs!A60)=1,3,"?"))) -> 1 | C60: regional-to-distant | D60: tp3 | E60: Tobacco regulations - advertising, front-of-pack labeling | F60: =IF(AND(all_inputs!E60=dropdown!Z$8, COUNTIF(dropdown!Z$9:Z$19,all_inputs!A60)=1), dropdown!U$13, 1) -> 1 | G60: =ui!B$4 -> 2025 | H60: =ui!B$5 -> 2050 | I60: China | J60: =VLOOKUP(ui!B$2,dropdown!M:O,3,FALSE) -> LIC | N60: 1 | R60: 1 | AA60: =VLOOKUP(all_inputs!E60,ui!A$29:B$33,2,FALSE) -> FALSE
A61: Ovarian cancer | B61: =IF(COUNTIF(dropdown!B$2:B$12,all_inputs!A61)=1,1,IF(COUNTIF(dropdown!C$2:C$4,all_inputs!A61)=1,2,IF(COUNTIF(dropdown!D$2:D$3,all_inputs!A61)=1,3,"?"))) -> 1 | C61: distant-to-dead | D61: cfr | E61: Tobacco regulations - advertising, front-of-pack labeling | F61: =IF(AND(all_inputs!E61=dropdown!Z$8, COUNTIF(dropdown!Z$9:Z$19,all_inputs!A61)=1), dropdown!U$14, 1) -> 1 | G61: =ui!B$4 -> 2025 | H61: =ui!B$5 -> 2050 | I61: China | J61: =VLOOKUP(ui!B$2,dropdown!M:O,3,FALSE) -> LIC | N61: 1 | R61: 1 | AA61: =VLOOKUP(all_inputs!E61,ui!A$29:B$33,2,FALSE) -> FALSE
A62: Pancreatic cancer | B62: =IF(COUNTIF(dropdown!B$2:B$12,all_inputs!A62)=1,1,IF(COUNTIF(dropdown!C$2:C$4,all_inputs!A62)=1,2,IF(COUNTIF(dropdown!D$2:D$3,all_inputs!A62)=1,3,"?"))) -> 1 | C62: well-to-precancer | D62: tp0 | E62: Tobacco regulations - advertising, front-of-pack labeling | F62: 1 | G62: =ui!B$4 -> 2025 | H62: =ui!B$5 -> 2050 | I62: China | J62: =VLOOKUP(ui!B$2,dropdown!M:O,3,FALSE) -> LIC | N62: 1 | R62: 1 | AA62: =VLOOKUP(all_inputs!E62,ui!A$29:B$33,2,FALSE) -> FALSE
A63: Pancreatic cancer | B63: =IF(COUNTIF(dropdown!B$2:B$12,all_inputs!A63)=1,1,IF(COUNTIF(dropdown!C$2:C$4,all_inputs!A63)=1,2,IF(COUNTIF(dropdown!D$2:D$3,all_inputs!A63)=1,3,"?"))) -> 1 | C63: well-to-local | D63: tp1 | E63: Tobacco regulations - advertising, front-of-pack labeling | F63: =IF(AND(all_inputs!E63=dropdown!Z$8, COUNTIF(dropdown!Z$9:Z$19,all_inputs!A63)=1), dropdown!U$10, 1) -> 1 | G63: =ui!B$4 -> 2025 | H63: =ui!B$5 -> 2050 | I63: China | J63: =VLOOKUP(ui!B$2,dropdown!M:O,3,FALSE) -> LIC | N63: 1 | R63: 1 | AA63: =VLOOKUP(all_inputs!E63,ui!A$29:B$33,2,FALSE) -> FALSE
A64: Pancreatic cancer | B64: =IF(COUNTIF(dropdown!B$2:B$12,all_inputs!A64)=1,1,IF(COUNTIF(dropdown!C$2:C$4,all_inputs!A64)=1,2,IF(COUNTIF(dropdown!D$2:D$3,all_inputs!A64)=1,3,"?"))) -> 1 | C64: precancer-to-local | D64: tp1 | E64: Tobacco regulations - advertising, front-of-pack labeling | F64: 1 | G64: =ui!B$4 -> 2025 | H64: =ui!B$5 -> 2050 | I64: China | J64: =VLOOKUP(ui!B$2,dropdown!M:O,3,FALSE) -> LIC | N64: 1 | R64: 1 | AA64: =VLOOKUP(all_inputs!E64,ui!A$29:B$33,2,FALSE) -> FALSE
A65: Pancreatic cancer | B65: =IF(COUNTIF(dropdown!B$2:B$12,all_inputs!A65)=1,1,IF(COUNTIF(dropdown!C$2:C$4,all_inputs!A65)=1,2,IF(COUNTIF(dropdown!D$2:D$3,all_inputs!A65)=1,3,"?"))) -> 1 | C65: local-to-regional | D65: tp2 | E65: Tobacco regulations - advertising, front-of-pack labeling | F65: =IF(AND(all_inputs!E65=dropdown!Z$8, COUNTIF(dropdown!Z$9:Z$19,all_inputs!A65)=1), dropdown!U$12, 1) -> 1 | G65: =ui!B$4 -> 2025 | H65: =ui!B$5 -> 2050 | I65: China | J65: =VLOOKUP(ui!B$2,dropdown!M:O,3,FALSE) -> LIC | N65: 1 | R65: 1 | AA65: =VLOOKUP(all_inputs!E65,ui!A$29:B$33,2,FALSE) -> FALSE
A66: Pancreatic cancer | B66: =IF(COUNTIF(dropdown!B$2:B$12,all_inputs!A66)=1,1,IF(COUNTIF(dropdown!C$2:C$4,all_inputs!A66)=1,2,IF(COUNTIF(dropdown!D$2:D$3,all_inputs!A66)=1,3,"?"))) -> 1 | C66: regional-to-distant | D66: tp3 | E66: Tobacco regulations - advertising, front-of-pack labeling | F66: =IF(AND(all_inputs!E66=dropdown!Z$8, COUNTIF(dropdown!Z$9:Z$19,all_inputs!A66)=1), dropdown!U$13, 1) -> 1 | G66: =ui!B$4 -> 2025 | H66: =ui!B$5 -> 2050 | I66: China | J66: =VLOOKUP(ui!B$2,dropdown!M:O,3,FALSE) -> LIC | N66: 1 | R66: 1 | AA66: =VLOOKUP(all_inputs!E66,ui!A$29:B$33,2,FALSE) -> FALSE
A67: Pancreatic cancer | B67: =IF(COUNTIF(dropdown!B$2:B$12,all_inputs!A67)=1,1,IF(COUNTIF(dropdown!C$2:C$4,all_inputs!A67)=1,2,IF(COUNTIF(dropdown!D$2:D$3,all_inputs!A67)=1,3,"?"))) -> 1 | C67: distant-to-dead | D67: cfr | E67: Tobacco regulations - advertising, front-of-pack labeling | F67: =IF(AND(all_inputs!E67=dropdown!Z$8, COUNTIF(dropdown!Z$9:Z$19,all_inputs!A67)=1), dropdown!U$14, 1) -> 1 | G67: =ui!B$4 -> 2025 | H67: =ui!B$5 -> 2050 | I67: China | J67: =VLOOKUP(ui!B$2,dropdown!M:O,3,FALSE) -> LIC | N67: 1 | R67: 1 | AA67: =VLOOKUP(all_inputs!E67,ui!A$29:B$33,2,FALSE) -> FALSE
A68: Prostate cancer | B68: =IF(COUNTIF(dropdown!B$2:B$12,all_inputs!A68)=1,1,IF(COUNTIF(dropdown!C$2:C$4,all_inputs!A68)=1,2,IF(COUNTIF(dropdown!D$2:D$3,all_inputs!A68)=1,3,"?"))) -> 2 | C68: well-to-precancer | D68: tp0 | E68: Tobacco regulations - advertising, front-of-pack labeling | F68: 1 | G68: =ui!B$4 -> 2025 | H68: =ui!B$5 -> 2050 | I68: China | J68: =VLOOKUP(ui!B$2,dropdown!M:O,3,FALSE) -> LIC | N68: 1 | R68: 1 | AA68: =VLOOKUP(all_inputs!E68,ui!A$29:B$33,2,FALSE) -> FALSE
A69: Prostate cancer | B69: =IF(COUNTIF(dropdown!B$2:B$12,all_inputs!A69)=1,1,IF(COUNTIF(dropdown!C$2:C$4,all_inputs!A69)=1,2,IF(COUNTIF(dropdown!D$2:D$3,all_inputs!A69)=1,3,"?"))) -> 2 | C69: well-to-local | D69: tp1 | E69: Tobacco regulations - advertising, front-of-pack labeling | F69: =IF(AND(all_inputs!E69=dropdown!Z$8, COUNTIF(dropdown!Z$9:Z$19,all_inputs!A69)=1), dropdown!U$10, 1) -> 1 | G69: =ui!B$4 -> 2025 | H69: =ui!B$5 -> 2050 | I69: China | J69: =VLOOKUP(ui!B$2,dropdown!M:O,3,FALSE) -> LIC | N69: 1 | R69: 1 | AA69: =VLOOKUP(all_inputs!E69,ui!A$29:B$33,2,FALSE) -> FALSE
A70: Prostate cancer | B70: =IF(COUNTIF(dropdown!B$2:B$12,all_inputs!A70)=1,1,IF(COUNTIF(dropdown!C$2:C$4,all_inputs!A70)=1,2,IF(COUNTIF(dropdown!D$2:D$3,all_inputs!A70)=1,3,"?"))) -> 2 | C70: precancer-to-local | D70: tp1 | E70: Tobacco regulations - advertising, front-of-pack labeling | F70: 1 | G70: =ui!B$4 -> 2025 | H70: =ui!B$5 -> 2050 | I70: China | J70: =VLOOKUP(ui!B$2,dropdown!M:O,3,FALSE) -> LIC | N70: 1 | R70: 1 | AA70: =VLOOKUP(all_inputs!E70,ui!A$29:B$33,2,FALSE) -> FALSE
A71: Prostate cancer | B71: =IF(COUNTIF(dropdown!B$2:B$12,all_inputs!A71)=1,1,IF(COUNTIF(dropdown!C$2:C$4,all_inputs!A71)=1,2,IF(COUNTIF(dropdown!D$2:D$3,all_inputs!A71)=1,3,"?"))) -> 2 | C71: local-to-regional | D71: tp2 | E71: Tobacco regulations - advertising, front-of-pack labeling | F71: =IF(AND(all_inputs!E71=dropdown!Z$8, COUNTIF(dropdown!Z$9:Z$19,all_inputs!A71)=1), dropdown!U$12, 1) -> 1 | G71: =ui!B$4 -> 2025 | H71: =ui!B$5 -> 2050 | I71: China | J71: =VLOOKUP(ui!B$2,dropdown!M:O,3,FALSE) -> LIC | N71: 1 | R71: 1 | AA71: =VLOOKUP(all_inputs!E71,ui!A$29:B$33,2,FALSE) -> FALSE
A72: Prostate cancer | B72: =IF(COUNTIF(dropdown!B$2:B$12,all_inputs!A72)=1,1,IF(COUNTIF(dropdown!C$2:C$4,all_inputs!A72)=1,2,IF(COUNTIF(dropdown!D$2:D$3,all_inputs!A72)=1,3,"?"))) -> 2 | C72: regional-to-distant | D72: tp3 | E72: Tobacco regulations - advertising, front-of-pack labeling | F72: =IF(AND(all_inputs!E72=dropdown!Z$8, COUNTIF(dropdown!Z$9:Z$19,all_inputs!A72)=1), dropdown!U$13, 1) -> 1 | G72: =ui!B$4 -> 2025 | H72: =ui!B$5 -> 2050 | I72: China | J72: =VLOOKUP(ui!B$2,dropdown!M:O,3,FALSE) -> LIC | N72: 1 | R72: 1 | AA72: =VLOOKUP(all_inputs!E72,ui!A$29:B$33,2,FALSE) -> FALSE
A73: Prostate cancer | B73: =IF(COUNTIF(dropdown!B$2:B$12,all_inputs!A73)=1,1,IF(COUNTIF(dropdown!C$2:C$4,all_inputs!A73)=1,2,IF(COUNTIF(dropdown!D$2:D$3,all_inputs!A73)=1,3,"?"))) -> 2 | C73: distant-to-dead | D73: cfr | E73: Tobacco regulations - advertising, front-of-pack labeling | F73: =IF(AND(all_inputs!E73=dropdown!Z$8, COUNTIF(dropdown!Z$9:Z$19,all_inputs!A73)=1), dropdown!U$14, 1) -> 1 | G73: =ui!B$4 -> 2025 | H73: =ui!B$5 -> 2050 | I73: China | J73: =VLOOKUP(ui!B$2,dropdown!M:O,3,FALSE) -> LIC | N73: 1 | R73: 1 | AA73: =VLOOKUP(all_inputs!E73,ui!A$29:B$33,2,FALSE) -> FALSE
A74: Stomach cancer | B74: =IF(COUNTIF(dropdown!B$2:B$12,all_inputs!A74)=1,1,IF(COUNTIF(dropdown!C$2:C$4,all_inputs!A74)=1,2,IF(COUNTIF(dropdown!D$2:D$3,all_inputs!A74)=1,3,"?"))) -> 1 | C74: well-to-precancer | D74: tp0 | E74: Tobacco regulations - advertising, front-of-pack labeling | F74: 1 | G74: =ui!B$4 -> 2025 | H74: =ui!B$5 -> 2050 | I74: China | J74: =VLOOKUP(ui!B$2,dropdown!M:O,3,FALSE) -> LIC | N74: 1 | R74: 1 | AA74: =VLOOKUP(all_inputs!E74,ui!A$29:B$33,2,FALSE) -> FALSE
A75: Stomach cancer | B75: =IF(COUNTIF(dropdown!B$2:B$12,all_inputs!A75)=1,1,IF(COUNTIF(dropdown!C$2:C$4,all_inputs!A75)=1,2,IF(COUNTIF(dropdown!D$2:D$3,all_inputs!A75)=1,3,"?"))) -> 1 | C75: well-to-local | D75: tp1 | E75: Tobacco regulations - advertising, front-of-pack labeling | F75: =IF(AND(all_inputs!E75=dropdown!Z$8, COUNTIF(dropdown!Z$9:Z$19,all_inputs!A75)=1), dropdown!U$10, 1) -> 1 | G75: =ui!B$4 -> 2025 | H75: =ui!B$5 -> 2050 | I75: China | J75: =VLOOKUP(ui!B$2,dropdown!M:O,3,FALSE) -> LIC | N75: 1 | R75: 1 | AA75: =VLOOKUP(all_inputs!E75,ui!A$29:B$33,2,FALSE) -> FALSE
A76: Stomach cancer | B76: =IF(COUNTIF(dropdown!B$2:B$12,all_inputs!A76)=1,1,IF(COUNTIF(dropdown!C$2:C$4,all_inputs!A76)=1,2,IF(COUNTIF(dropdown!D$2:D$3,all_inputs!A76)=1,3,"?"))) -> 1 | C76: precancer-to-local | D76: tp1 | E76: Tobacco regulations - advertising, front-of-pack labeling | F76: 1 | G76: =ui!B$4 -> 2025 | H76: =ui!B$5 -> 2050 | I76: China | J76: =VLOOKUP(ui!B$2,dropdown!M:O,3,FALSE) -> LIC | N76: 1 | R76: 1 | AA76: =VLOOKUP(all_inputs!E76,ui!A$29:B$33,2,FALSE) -> FALSE
A77: Stomach cancer | B77: =IF(COUNTIF(dropdown!B$2:B$12,all_inputs!A77)=1,1,IF(COUNTIF(dropdown!C$2:C$4,all_inputs!A77)=1,2,IF(COUNTIF(dropdown!D$2:D$3,all_inputs!A77)=1,3,"?"))) -> 1 | C77: local-to-regional | D77: tp2 | E77: Tobacco regulations - advertising, front-of-pack labeling | F77: =IF(AND(all_inputs!E77=dropdown!Z$8, COUNTIF(dropdown!Z$9:Z$19,all_inputs!A77)=1), dropdown!U$12, 1) -> 1 | G77: =ui!B$4 -> 2025 | H77: =ui!B$5 -> 2050 | I77: China | J77: =VLOOKUP(ui!B$2,dropdown!M:O,3,FALSE) -> LIC | N77: 1 | R77: 1 | AA77: =VLOOKUP(all_inputs!E77,ui!A$29:B$33,2,FALSE) -> FALSE
A78: Stomach cancer | B78: =IF(COUNTIF(dropdown!B$2:B$12,all_inputs!A78)=1,1,IF(COUNTIF(dropdown!C$2:C$4,all_inputs!A78)=1,2,IF(COUNTIF(dropdown!D$2:D$3,all_inputs!A78)=1,3,"?"))) -> 1 | C78: regional-to-distant | D78: tp3 | E78: Tobacco regulations - advertising, front-of-pack labeling | F78: =IF(AND(all_inputs!E78=dropdown!Z$8, COUNTIF(dropdown!Z$9:Z$19,all_inputs!A78)=1), dropdown!U$13, 1) -> 1 | G78: =ui!B$4 -> 2025 | H78: =ui!B$5 -> 2050 | I78: China | J78: =VLOOKUP(ui!B$2,dropdown!M:O,3,FALSE) -> LIC | N78: 1 | R78: 1 | AA78: =VLOOKUP(all_inputs!E78,ui!A$29:B$33,2,FALSE) -> FALSE
A79: Stomach cancer | B79: =IF(COUNTIF(dropdown!B$2:B$12,all_inputs!A79)=1,1,IF(COUNTIF(dropdown!C$2:C$4,all_inputs!A79)=1,2,IF(COUNTIF(dropdown!D$2:D$3,all_inputs!A79)=1,3,"?"))) -> 1 | C79: distant-to-dead | D79: cfr | E79: Tobacco regulations - advertising, front-of-pack labeling | F79: =IF(AND(all_inputs!E79=dropdown!Z$8, COUNTIF(dropdown!Z$9:Z$19,all_inputs!A79)=1), dropdown!U$14, 1) -> 1 | G79: =ui!B$4 -> 2025 | H79: =ui!B$5 -> 2050 | I79: China | J79: =VLOOKUP(ui!B$2,dropdown!M:O,3,FALSE) -> LIC | N79: 1 | R79: 1 | AA79: =VLOOKUP(all_inputs!E79,ui!A$29:B$33,2,FALSE) -> FALSE
A80: Thyroid cancer | B80: =IF(COUNTIF(dropdown!B$2:B$12,all_inputs!A80)=1,1,IF(COUNTIF(dropdown!C$2:C$4,all_inputs!A80)=1,2,IF(COUNTIF(dropdown!D$2:D$3,all_inputs!A80)=1,3,"?"))) -> 1 | C80: well-to-precancer | D80: tp0 | E80: Tobacco regulations - advertising, front-of-pack labeling | F80: 1 | G80: =ui!B$4 -> 2025 | H80: =ui!B$5 -> 2050 | I80: China | J80: =VLOOKUP(ui!B$2,dropdown!M:O,3,FALSE) -> LIC | N80: 1 | R80: 1 | AA80: =VLOOKUP(all_inputs!E80,ui!A$29:B$33,2,FALSE) -> FALSE
A81: Thyroid cancer | B81: =IF(COUNTIF(dropdown!B$2:B$12,all_inputs!A81)=1,1,IF(COUNTIF(dropdown!C$2:C$4,all_inputs!A81)=1,2,IF(COUNTIF(dropdown!D$2:D$3,all_inputs!A81)=1,3,"?"))) -> 1 | C81: well-to-local | D81: tp1 | E81: Tobacco regulations - advertising, front-of-pack labeling | F81: =IF(AND(all_inputs!E81=dropdown!Z$8, COUNTIF(dropdown!Z$9:Z$19,all_inputs!A81)=1), dropdown!U$10, 1) -> 1 | G81: =ui!B$4 -> 2025 | H81: =ui!B$5 -> 2050 | I81: China | J81: =VLOOKUP(ui!B$2,dropdown!M:O,3,FALSE) -> LIC | N81: 1 | R81: 1 | AA81: =VLOOKUP(all_inputs!E81,ui!A$29:B$33,2,FALSE) -> FALSE
A82: Thyroid cancer | B82: =IF(COUNTIF(dropdown!B$2:B$12,all_inputs!A82)=1,1,IF(COUNTIF(dropdown!C$2:C$4,all_inputs!A82)=1,2,IF(COUNTIF(dropdown!D$2:D$3,all_inputs!A82)=1,3,"?"))) -> 1 | C82: precancer-to-local | D82: tp1 | E82: Tobacco regulations - advertising, front-of-pack labeling | F82: 1 | G82: =ui!B$4 -> 2025 | H82: =ui!B$5 -> 2050 | I82: China | J82: =VLOOKUP(ui!B$2,dropdown!M:O,3,FALSE) -> LIC | N82: 1 | R82: 1 | AA82: =VLOOKUP(all_inputs!E82,ui!A$29:B$33,2,FALSE) -> FALSE
A83: Thyroid cancer | B83: =IF(COUNTIF(dropdown!B$2:B$12,all_inputs!A83)=1,1,IF(COUNTIF(dropdown!C$2:C$4,all_inputs!A83)=1,2,IF(COUNTIF(dropdown!D$2:D$3,all_inputs!A83)=1,3,"?"))) -> 1 | C83: local-to-regional | D83: tp2 | E83: Tobacco regulations - advertising, front-of-pack labeling | F83: =IF(AND(all_inputs!E83=dropdown!Z$8, COUNTIF(dropdown!Z$9:Z$19,all_inputs!A83)=1), dropdown!U$12, 1) -> 1 | G83: =ui!B$4 -> 2025 | H83: =ui!B$5 -> 2050 | I83: China | J83: =VLOOKUP(ui!B$2,dropdown!M:O,3,FALSE) -> LIC | N83: 1 | R83: 1 | AA83: =VLOOKUP(all_inputs!E83,ui!A$29:B$33,2,FALSE) -> FALSE
A84: Thyroid cancer | B84: =IF(COUNTIF(dropdown!B$2:B$12,all_inputs!A84)=1,1,IF(COUNTIF(dropdown!C$2:C$4,all_inputs!A84)=1,2,IF(COUNTIF(dropdown!D$2:D$3,all_inputs!A84)=1,3,"?"))) -> 1 | C84: regional-to-distant | D84: tp3 | E84: Tobacco regulations - advertising, front-of-pack labeling | F84: =IF(AND(all_inputs!E84=dropdown!Z$8, COUNTIF(dropdown!Z$9:Z$19,all_inputs!A84)=1), dropdown!U$13, 1) -> 1 | G84: =ui!B$4 -> 2025 | H84: =ui!B$5 -> 2050 | I84: China | J84: =VLOOKUP(ui!B$2,dropdown!M:O,3,FALSE) -> LIC | N84: 1 | R84: 1 | AA84: =VLOOKUP(all_inputs!E84,ui!A$29:B$33,2,FALSE) -> FALSE
A85: Thyroid cancer | B85: =IF(COUNTIF(dropdown!B$2:B$12,all_inputs!A85)=1,1,IF(COUNTIF(dropdown!C$2:C$4,all_inputs!A85)=1,2,IF(COUNTIF(dropdown!D$2:D$3,all_inputs!A85)=1,3,"?"))) -> 1 | C85: distant-to-dead | D85: cfr | E85: Tobacco regulations - advertising, front-of-pack labeling | F85: =IF(AND(all_inputs!E85=dropdown!Z$8, COUNTIF(dropdown!Z$9:Z$19,all_inputs!A85)=1), dropdown!U$14, 1) -> 1 | G85: =ui!B$4 -> 2025 | H85: =ui!B$5 -> 2050 | I85: China | J85: =VLOOKUP(ui!B$2,dropdown!M:O,3,FALSE) -> LIC | N85: 1 | R85: 1 | AA85: =VLOOKUP(all_inputs!E85,ui!A$29:B$33,2,FALSE) -> FALSE
A86: Tracheal, bronchus, and lung cancer | B86: =IF(COUNTIF(dropdown!B$2:B$12,all_inputs!A86)=1,1,IF(COUNTIF(dropdown!C$2:C$4,all_inputs!A86)=1,2,IF(COUNTIF(dropdown!D$2:D$3,all_inputs!A86)=1,3,"?"))) -> 2 | C86: well-to-precancer | D86: tp0 | E86: Tobacco regulations - advertising, front-of-pack labeling | F86: 1 | G86: =ui!B$4 -> 2025 | H86: =ui!B$5 -> 2050 | I86: China | J86: =VLOOKUP(ui!B$2,dropdown!M:O,3,FALSE) -> LIC | N86: 1 | R86: 1 | AA86: =VLOOKUP(all_inputs!E86,ui!A$29:B$33,2,FALSE) -> FALSE
A87: Tracheal, bronchus, and lung cancer | B87: =IF(COUNTIF(dropdown!B$2:B$12,all_inputs!A87)=1,1,IF(COUNTIF(dropdown!C$2:C$4,all_inputs!A87)=1,2,IF(COUNTIF(dropdown!D$2:D$3,all_inputs!A87)=1,3,"?"))) -> 2 | C87: well-to-local | D87: tp1 | E87: Tobacco regulations - advertising, front-of-pack labeling | F87: =IF(AND(all_inputs!E87=dropdown!Z$8, COUNTIF(dropdown!Z$9:Z$19,all_inputs!A87)=1), dropdown!U$10, 1) -> 1 | G87: =ui!B$4 -> 2025 | H87: =ui!B$5 -> 2050 | I87: China | J87: =VLOOKUP(ui!B$2,dropdown!M:O,3,FALSE) -> LIC | N87: 1 | R87: 1 | AA87: =VLOOKUP(all_inputs!E87,ui!A$29:B$33,2,FALSE) -> FALSE
A88: Tracheal, bronchus, and lung cancer | B88: =IF(COUNTIF(dropdown!B$2:B$12,all_inputs!A88)=1,1,IF(COUNTIF(dropdown!C$2:C$4,all_inputs!A88)=1,2,IF(COUNTIF(dropdown!D$2:D$3,all_inputs!A88)=1,3,"?"))) -> 2 | C88: precancer-to-local | D88: tp1 | E88: Tobacco regulations - advertising, front-of-pack labeling | F88: 1 | G88: =ui!B$4 -> 2025 | H88: =ui!B$5 -> 2050 | I88: China | J88: =VLOOKUP(ui!B$2,dropdown!M:O,3,FALSE) -> LIC | N88: 1 | R88: 1 | AA88: =VLOOKUP(all_inputs!E88,ui!A$29:B$33,2,FALSE) -> FALSE
A89: Tracheal, bronchus, and lung cancer | B89: =IF(COUNTIF(dropdown!B$2:B$12,all_inputs!A89)=1,1,IF(COUNTIF(dropdown!C$2:C$4,all_inputs!A89)=1,2,IF(COUNTIF(dropdown!D$2:D$3,all_inputs!A89)=1,3,"?"))) -> 2 | C89: local-to-regional | D89: tp2 | E89: Tobacco regulations - advertising, front-of-pack labeling | F89: =IF(AND(all_inputs!E89=dropdown!Z$8, COUNTIF(dropdown!Z$9:Z$19,all_inputs!A89)=1), dropdown!U$12, 1) -> 1 | G89: =ui!B$4 -> 2025 | H89: =ui!B$5 -> 2050 | I89: China | J89: =VLOOKUP(ui!B$2,dropdown!M:O,3,FALSE) -> LIC | N89: 1 | R89: 1 | AA89: =VLOOKUP(all_inputs!E89,ui!A$29:B$33,2,FALSE) -> FALSE
A90: Tracheal, bronchus, and lung cancer | B90: =IF(COUNTIF(dropdown!B$2:B$12,all_inputs!A90)=1,1,IF(COUNTIF(dropdown!C$2:C$4,all_inputs!A90)=1,2,IF(COUNTIF(dropdown!D$2:D$3,all_inputs!A90)=1,3,"?"))) -> 2 | C90: regional-to-distant | D90: tp3 | E90: Tobacco regulations - advertising, front-of-pack labeling | F90: =IF(AND(all_inputs!E90=dropdown!Z$8, COUNTIF(dropdown!Z$9:Z$19,all_inputs!A90)=1), dropdown!U$13, 1) -> 1 | G90: =ui!B$4 -> 2025 | H90: =ui!B$5 -> 2050 | I90: China | J90: =VLOOKUP(ui!B$2,dropdown!M:O,3,FALSE) -> LIC | N90: 1 | R90: 1 | AA90: =VLOOKUP(all_inputs!E90,ui!A$29:B$33,2,FALSE) -> FALSE
A91: Tracheal, bronchus, and lung cancer | B91: =IF(COUNTIF(dropdown!B$2:B$12,all_inputs!A91)=1,1,IF(COUNTIF(dropdown!C$2:C$4,all_inputs!A91)=1,2,IF(COUNTIF(dropdown!D$2:D$3,all_inputs!A91)=1,3,"?"))) -> 2 | C91: distant-to-dead | D91: cfr | E91: Tobacco regulations - advertising, front-of-pack labeling | F91: =IF(AND(all_inputs!E91=dropdown!Z$8, COUNTIF(dropdown!Z$9:Z$19,all_inputs!A91)=1), dropdown!U$14, 1) -> 1 | G91: =ui!B$4 -> 2025 | H91: =ui!B$5 -> 2050 | I91: China | J91: =VLOOKUP(ui!B$2,dropdown!M:O,3,FALSE) -> LIC | N91: 1 | R91: 1 | AA91: =VLOOKUP(all_inputs!E91,ui!A$29:B$33,2,FALSE) -> FALSE
A92: Uterine cancer | B92: =IF(COUNTIF(dropdown!B$2:B$12,all_inputs!A92)=1,1,IF(COUNTIF(dropdown!C$2:C$4,all_inputs!A92)=1,2,IF(COUNTIF(dropdown!D$2:D$3,all_inputs!A92)=1,3,"?"))) -> 1 | C92: well-to-precancer | D92: tp0 | E92: Tobacco regulations - advertising, front-of-pack labeling | F92: 1 | G92: =ui!B$4 -> 2025 | H92: =ui!B$5 -> 2050 | I92: China | J92: =VLOOKUP(ui!B$2,dropdown!M:O,3,FALSE) -> LIC | N92: 1 | R92: 1 | AA92: =VLOOKUP(all_inputs!E92,ui!A$29:B$33,2,FALSE) -> FALSE
A93: Uterine cancer | B93: =IF(COUNTIF(dropdown!B$2:B$12,all_inputs!A93)=1,1,IF(COUNTIF(dropdown!C$2:C$4,all_inputs!A93)=1,2,IF(COUNTIF(dropdown!D$2:D$3,all_inputs!A93)=1,3,"?"))) -> 1 | C93: well-to-local | D93: tp1 | E93: Tobacco regulations - advertising, front-of-pack labeling | F93: =IF(AND(all_inputs!E93=dropdown!Z$8, COUNTIF(dropdown!Z$9:Z$19,all_inputs!A93)=1), dropdown!U$10, 1) -> 1 | G93: =ui!B$4 -> 2025 | H93: =ui!B$5 -> 2050 | I93: China | J93: =VLOOKUP(ui!B$2,dropdown!M:O,3,FALSE) -> LIC | N93: 1 | R93: 1 | AA93: =VLOOKUP(all_inputs!E93,ui!A$29:B$33,2,FALSE) -> FALSE
A94: Uterine cancer | B94: =IF(COUNTIF(dropdown!B$2:B$12,all_inputs!A94)=1,1,IF(COUNTIF(dropdown!C$2:C$4,all_inputs!A94)=1,2,IF(COUNTIF(dropdown!D$2:D$3,all_inputs!A94)=1,3,"?"))) -> 1 | C94: precancer-to-local | D94: tp1 | E94: Tobacco regulations - advertising, front-of-pack labeling | F94: 1 | G94: =ui!B$4 -> 2025 | H94: =ui!B$5 -> 2050 | I94: China | J94: =VLOOKUP(ui!B$2,dropdown!M:O,3,FALSE) -> LIC | N94: 1 | R94: 1 | AA94: =VLOOKUP(all_inputs!E94,ui!A$29:B$33,2,FALSE) -> FALSE
A95: Uterine cancer | B95: =IF(COUNTIF(dropdown!B$2:B$12,all_inputs!A95)=1,1,IF(COUNTIF(dropdown!C$2:C$4,all_inputs!A95)=1,2,IF(COUNTIF(dropdown!D$2:D$3,all_inputs!A95)=1,3,"?"))) -> 1 | C95: local-to-regional | D95: tp2 | E95: Tobacco regulations - advertising, front-of-pack labeling | F95: =IF(AND(all_inputs!E95=dropdown!Z$8, COUNTIF(dropdown!Z$9:Z$19,all_inputs!A95)=1), dropdown!U$12, 1) -> 1 | G95: =ui!B$4 -> 2025 | H95: =ui!B$5 -> 2050 | I95: China | J95: =VLOOKUP(ui!B$2,dropdown!M:O,3,FALSE) -> LIC | N95: 1 | R95: 1 | AA95: =VLOOKUP(all_inputs!E95,ui!A$29:B$33,2,FALSE) -> FALSE
A96: Uterine cancer | B96: =IF(COUNTIF(dropdown!B$2:B$12,all_inputs!A96)=1,1,IF(COUNTIF(dropdown!C$2:C$4,all_inputs!A96)=1,2,IF(COUNTIF(dropdown!D$2:D$3,all_inputs!A96)=1,3,"?"))) -> 1 | C96: regional-to-distant | D96: tp3 | E96: Tobacco regulations - advertising, front-of-pack labeling | F96: =IF(AND(all_inputs!E96=dropdown!Z$8, COUNTIF(dropdown!Z$9:Z$19,all_inputs!A96)=1), dropdown!U$13, 1) -> 1 | G96: =ui!B$4 -> 2025 | H96: =ui!B$5 -> 2050 | I96: China | J96: =VLOOKUP(ui!B$2,dropdown!M:O,3,FALSE) -> LIC | N96: 1 | R96: 1 | AA96: =VLOOKUP(all_inputs!E96,ui!A$29:B$33,2,FALSE) -> FALSE
A97: Uterine cancer | B97: =IF(COUNTIF(dropdown!B$2:B$12,all_inputs!A97)=1,1,IF(COUNTIF(dropdown!C$2:C$4,all_inputs!A97)=1,2,IF(COUNTIF(dropdown!D$2:D$3,all_inputs!A97)=1,3,"?"))) -> 1 | C97: distant-to-dead | D97: cfr | E97: Tobacco regulations - advertising, front-of-pack labeling | F97: =IF(AND(all_inputs!E97=dropdown!Z$8, COUNTIF(dropdown!Z$9:Z$19,all_inputs!A97)=1), dropdown!U$14, 1) -> 1 | G97: =ui!B$4 -> 2025 | H97: =ui!B$5 -> 2050 | I97: China | J97: =VLOOKUP(ui!B$2,dropdown!M:O,3,FALSE) -> LIC | N97: 1 | R97: 1 | AA97: =VLOOKUP(all_inputs!E97,ui!A$29:B$33,2,FALSE) -> FALSE
A98: Bladder cancer | B98: =IF(COUNTIF(dropdown!B$2:B$12,all_inputs!A98)=1,1,IF(COUNTIF(dropdown!C$2:C$4,all_inputs!A98)=1,2,IF(COUNTIF(dropdown!D$2:D$3,all_inputs!A98)=1,3,"?"))) -> 1 | C98: well-to-precancer | D98: tp0 | E98: Tobacco mass media campaigns | F98: =IF(AND(all_inputs!E98=dropdown!AA$8, COUNTIF(dropdown!AA$9:AA$19,all_inputs!A98)=1), dropdown!V$9, 1) -> 1 | G98: =ui!B$4 -> 2025 | H98: =ui!B$5 -> 2050 | I98: China | J98: =VLOOKUP(ui!B$2,dropdown!M:O,3,FALSE) -> LIC | N98: 1 | R98: 1 | AA98: =VLOOKUP(all_inputs!E98,ui!A$29:B$33,2,FALSE) -> FALSE
A99: Bladder cancer | B99: =IF(COUNTIF(dropdown!B$2:B$12,all_inputs!A99)=1,1,IF(COUNTIF(dropdown!C$2:C$4,all_inputs!A99)=1,2,IF(COUNTIF(dropdown!D$2:D$3,all_inputs!A99)=1,3,"?"))) -> 1 | C99: well-to-local | D99: tp1 | E99: Tobacco mass media campaigns | F99: =IF(AND(all_inputs!E99=dropdown!AA$8, COUNTIF(dropdown!AA$9:AA$19,all_inputs!A99)=1), dropdown!V$10, 1) -> 1 | G99: =ui!B$4 -> 2025 | H99: =ui!B$5 -> 2050 | I99: China | J99: =VLOOKUP(ui!B$2,dropdown!M:O,3,FALSE) -> LIC | N99: 1 | R99: 1 | AA99: =VLOOKUP(all_inputs!E99,ui!A$29:B$33,2,FALSE) -> FALSE
A100: Bladder cancer | B100: =IF(COUNTIF(dropdown!B$2:B$12,all_inputs!A100)=1,1,IF(COUNTIF(dropdown!C$2:C$4,all_inputs!A100)=1,2,IF(COUNTIF(dropdown!D$2:D$3,all_inputs!A100)=1,3,"?"))) -> 1 | C100: precancer-to-local | D100: tp1 | E100: Tobacco mass media campaigns | F100: =IF(AND(all_inputs!E100=dropdown!AA$8, COUNTIF(dropdown!AA$9:AA$19,all_inputs!A100)=1), dropdown!V$11, 1) -> 1 | G100: =ui!B$4 -> 2025 | H100: =ui!B$5 -> 2050 | I100: China | J100: =VLOOKUP(ui!B$2,dropdown!M:O,3,FALSE) -> LIC | N100: 1 | R100: 1 | AA100: =VLOOKUP(all_inputs!E100,ui!A$29:B$33,2,FALSE) -> FALSE
...

Sheet dropdown
A1: Cancer | B1: Cat 1 | C1: Cat 2 | D1: Cat 3 | F1: Targets | I1: setting | K1: include | M1: location | N1: Code | O1: setting | Q1: year | R1: Scaleup end | T1: Intervention pacakges | U1: effect_on_tp0 | V1: effect_on_tp1 | W1: effect_on_tp1_cat3 | X1: effect_on_tp2 | Y1: effect_on_tp3 | Z1: effect_on_cfr
A2: Bladder cancer | B2: Bladder cancer | C2: Breast cancer | D2: Cervical cancer | F2: screening coverage | G2: 0.8 | I2: HIC | K2: TRUE | M2: Afghanistan | N2: AFG | O2: LIC | Q2: 2005 | R2: 2006 | T2: Tobacco control | U2: 0.3 | V2: 0.5 | W2: 0.5 | X2: 0.7 | Y2: 0.8 | Z2: 0.6 | AA2: Bladder cancer | AB2: Cervical cancer | AC2: Colon and rectum cancer | AD2: Esophageal cancer | AE2: Lip and oral cavity cancer | AF2: Liver cancer | AG2: Nasopharynx cancer | AH2: Other pharynx cancer | AI2: Pancreatic cancer | AJ2: Stomach cancer | AK2: Tracheal, bronchus, and lung cancer
A3: Breast cancer | B3: Esophageal cancer | C3: Prostate cancer | D3: Colon and rectum cancer | F3: Diagnoses coverage | G3: 0.8 | I3: UMIC | K3: FALSE | M3: Albania | N3: ALB | O3: UMIC | Q3: 2006 | R3: 2007 | T3: Alcohol control | U3: 1 | V3: 0.8 | W3: 0.9 | X3: 1 | Y3: 1 | Z3: 0.9 | AA3: Breast cancer | AB3: Colon and rectum cancer | AC3: Esophageal cancer | AD3: Lip and oral cavity cancer | AE3: Liver cancer | AF3: Nasopharynx cancer | AG3: Other pharynx cancer | AH3: Ovarian cancer | AI3: Pancreatic cancer | AJ3: Stomach cancer
A4: Cervical cancer | B4: Lip and oral cavity cancer | C4: Tracheal, bronchus, and lung cancer | F4: Early detection prop | G4: 0.9 | I4: LMIC | M4: Algeria | N4: DZA | O4: LMIC | Q4: 2007 | R4: 2008 | T4: Standard of care treatment | U4: 0.3 | V4: 0.2 | W4: 0.2 | X4: 0.4 | Y4: 0.5 | Z4: 0.6 | AA4: Bladder cancer | AB4: Breast cancer | AC4: Cervical cancer | AD4: Colon and rectum cancer | AE4: Esophageal cancer | AF4: Lip and oral cavity cancer | AG4: Liver cancer | AH4: Nasopharynx cancer | AI4: Other pharynx cancer | AJ4: Ovarian cancer | AK4: Pancreatic cancer | AL4: Prostate cancer | AM4: Stomach cancer | AN4: Thyroid cancer | AO4: Tracheal, bronchus, and lung cancer | AP4: Uterine cancer
A5: Colon and rectum cancer | B5: Liver cancer | F5: Linkage to care | G5: 0.9 | I5: LIC | M5: Angola | N5: AGO | O5: LMIC | Q5: 2008 | R5: 2009 | T5: Palliative care | U5: 1 | V5: 1 | W5: 1 | X5: 1 | Y5: 1 | Z5: 0.5 | AA5: Bladder cancer | AB5: Breast cancer | AC5: Cervical cancer | AD5: Colon and rectum cancer | AE5: Esophageal cancer | AF5: Lip and oral cavity cancer | AG5: Liver cancer | AH5: Nasopharynx cancer | AI5: Other pharynx cancer | AJ5: Ovarian cancer | AK5: Pancreatic cancer | AL5: Prostate cancer | AM5: Stomach cancer | AN5: Thyroid cancer | AO5: Tracheal, bronchus, and lung cancer | AP5: Uterine cancer
A6: Esophageal cancer | B6: Nasopharynx cancer | F6: Retention in care | G6: 0.9 | M6: Antigua and Barbuda | N6: ATG | O6: HIC | Q6: 2009 | R6: 2010
A7: Lip and oral cavity cancer | B7: Other pharynx cancer | M7: Argentina | N7: ARG | O7: UMIC | Q7: 2010 | R7: 2011
A8: Liver cancer | B8: Ovarian cancer | M8: Armenia | N8: ARM | O8: UMIC | Q8: 2011 | R8: 2012 | U8: Tobacco control | V8: Alcohol control | W8: Standard of care treatment | X8: Palliative care | Z8: Tobacco control | AA8: Alcohol control | AB8: Standard of care treatment | AC8: Palliative care
A9: Nasopharynx cancer | B9: Pancreatic cancer | M9: Australia | N9: AUS | O9: HIC | Q9: 2012 | R9: 2013 | T9: effect_on_tp0 | U9: 0.3 | V9: 1 | W9: 0.3 | X9: 1 | Z9: Bladder cancer | AA9: Breast cancer | AB9: Bladder cancer | AC9: Bladder cancer
A10: Other pharynx cancer | B10: Stomach cancer | D10: Stage distribution | M10: Austria | N10: AUT | O10: HIC | Q10: 2013 | R10: 2014 | T10: effect_on_tp1 | U10: 0.5 | V10: 0.8 | W10: 0.2 | X10: 1 | Z10: Cervical cancer | AA10: Colon and rectum cancer | AB10: Breast cancer | AC10: Breast cancer
A11: Ovarian cancer | B11: Thyroid cancer | D11: Assumed | M11: Azerbaijan | N11: AZE | O11: UMIC | Q11: 2014 | R11: 2015 | T11: effect_on_tp1_cat3 | U11: 0.5 | V11: 0.9 | W11: 0.2 | X11: 1 | Z11: Colon and rectum cancer | AA11: Esophageal cancer | AB11: Cervical cancer | AC11: Cervical cancer
A12: Pancreatic cancer | B12: Uterine cancer | D12: User-defined | M12: Bahamas | N12: BHS | O12: HIC | Q12: 2015 | R12: 2016 | T12: effect_on_tp2 | U12: 0.7 | V12: 1 | W12: 0.4 | X12: 1 | Z12: Esophageal cancer | AA12: Lip and oral cavity cancer | AB12: Colon and rectum cancer | AC12: Colon and rectum cancer
A13: Prostate cancer | M13: Bahrain | N13: BHR | O13: HIC | Q13: 2016 | R13: 2017 | T13: effect_on_tp3 | U13: 0.8 | V13: 1 | W13: 0.5 | X13: 1 | Z13: Lip and oral cavity cancer | AA13: Liver cancer | AB13: Esophageal cancer | AC13: Esophageal cancer
A14: Stomach cancer | M14: Bangladesh | N14: BGD | O14: LMIC | Q14: 2017 | R14: 2018 | T14: effect_on_cfr | U14: 0.6 | V14: 0.9 | W14: 0.6 | X14: 0.5 | Z14: Liver cancer | AA14: Nasopharynx cancer | AB14: Lip and oral cavity cancer | AC14: Lip and oral cavity cancer
A15: Thyroid cancer | M15: Barbados | N15: BRB | O15: HIC | Q15: 2018 | R15: 2019 | Z15: Nasopharynx cancer | AA15: Other pharynx cancer | AB15: Liver cancer | AC15: Liver cancer
A16: Tracheal, bronchus, and lung cancer | M16: Belarus | N16: BLR | O16: UMIC | Q16: 2019 | R16: 2020 | Z16: Other pharynx cancer | AA16: Ovarian cancer | AB16: Nasopharynx cancer | AC16: Nasopharynx cancer
A17: Uterine cancer | M17: Belgium | N17: BEL | O17: HIC | Q17: 2020 | R17: 2021 | Z17: Pancreatic cancer | AA17: Pancreatic cancer | AB17: Other pharynx cancer | AC17: Other pharynx cancer
M18: Belize | N18: BLZ | O18: UMIC | Q18: 2021 | R18: 2022 | Z18: Stomach cancer | AA18: Stomach cancer | AB18: Ovarian cancer | AC18: Ovarian cancer
M19: Benin | N19: BEN | O19: LMIC | Q19: 2022 | R19: 2023 | Z19: Tracheal, bronchus, and lung cancer | AB19: Pancreatic cancer | AC19: Pancreatic cancer
M20: Bhutan | N20: BTN | O20: LMIC | Q20: 2023 | R20: 2024 | AB20: Prostate cancer | AC20: Prostate cancer
M21: Bolivia | N21: BOL | O21: LMIC | Q21: 2024 | R21: 2025 | AB21: Stomach cancer | AC21: Stomach cancer
M22: Bosnia and Herzegovina | N22: BIH | O22: UMIC | Q22: 2025 | R22: 2026 | AB22: Thyroid cancer | AC22: Thyroid cancer
M23: Botswana | N23: BWA | O23: UMIC | Q23: 2026 | R23: 2027 | AB23: Tracheal, bronchus, and lung cancer | AC23: Tracheal, bronchus, and lung cancer
M24: Brazil | N24: BRA | O24: UMIC | Q24: 2027 | R24: 2028 | AB24: Uterine cancer | AC24: Uterine cancer
M25: Brunei Darussalam | N25: BRN | O25: HIC | Q25: 2028 | R25: 2029
M26: Bulgaria | N26: BGR | O26: UMIC | Q26: 2029 | R26: 2030
M27: Burkina Faso | N27: BFA | O27: LIC | Q27: 2030 | R27: 2031
M28: Burundi | N28: BDI | O28: LIC | Q28: 2031 | R28: 2032
M29: Cambodia | N29: KHM | O29: LMIC | Q29: 2032 | R29: 2033
M30: Cameroon | N30: CMR | O30: LMIC | Q30: 2033 | R30: 2034
M31: Canada | N31: CAN | O31: HIC | Q31: 2034 | R31: 2035
M32: Cape Verde | N32: CPV | O32: LMIC | Q32: 2035 | R32: 2036
M33: Central African Republic | N33: CAF | O33: LIC | Q33: 2036 | R33: 2037
M34: Chad | N34: TCD | O34: LIC | Q34: 2037 | R34: 2038
M35: Chile | N35: CHL | O35: HIC | Q35: 2038 | R35: 2039
M36: China | N36: CHN | O36: UMIC | Q36: 2039 | R36: 2040
... M46: Democratic Republic of the Congo | N46: COD | O46: LIC | Q46: 2049 | R46: 2050
M47: Denmark | N47: DNK | O47: HIC | Q47: 2050
M48: Djibouti | N48: DJI | O48: LMIC
M49: Dominican Republic | N49: DMA | O49: UMIC
M50: Dominican Republic | N50: DOM | O50: UMIC
M51: Ecuador | N51: ECU | O51: UMIC
M52: Egypt | N52: EGY | O52: LMIC
M53: El Salvador | N53: SLV | O53: UMIC
M54: Equatorial Guinea | N54: GNQ | O54: UMIC
M55: Eritrea | N55: ERI | O55: LIC
M56: Estonia | N56: EST | O56: HIC
M57: Eswatini | N57: SWZ | O57: LMIC
M58: Ethiopia | N58: ETH | O58: LIC
M59: Fiji | N59: FJI | O59: UMIC
... M184: Vanuatu | N184: VUT | O184: LMIC
M185: Venezuela | N185: VEN | O185: #N/A
M186: Vietnam | N186: VNM | O186: LMIC
M187: Virgin Islands | N187: VIR | O187: HIC
M188: Yemen | N188: YEM | O188: LIC
M189: Zambia | N189: ZMB | O189: LMIC
M190: Zimbabwe | N190: ZWE | O190: LMIC

Sheet begin
A1: cause | B1: Intervention | C1: Setting | D1: Scaleup | E1: Screened | F1: Diagnosed | G1: Treated | H1: Completed | I1: Precancer | J1: Local | K1: Regional | L1: Distant | M1: Total
A2: Bladder cancer | B2: No | C2: HIC | D2: begin | E2: 0 | F2: 0.5 | G2: =F2*dropdown!G$4 -> 0.45 | H2: =G2*dropdown!G$5 -> 0.405 | I2: 0 | J2: 1 | K2: 0 | L2: 0 | M2: =SUM(I2:L2) -> 1
A3: Bladder cancer | B3: No | C3: UMIC | D3: begin | E3: 0 | F3: 0.4 | G3: =F3*dropdown!G$4 -> 0.36 | H3: =G3*dropdown!G$5 -> 0.324 | I3: 0 | J3: 1 | K3: 0 | L3: 0 | M3: =SUM(I3:L3) -> 1
A4: Bladder cancer | B4: No | C4: LMIC | D4: begin | E4: 0 | F4: 0.3 | G4: =F4*dropdown!G$4 -> 0.27 | H4: =G4*dropdown!G$5 -> 0.243 | I4: 0 | J4: 1 | K4: 0 | L4: 0 | M4: =SUM(I4:L4) -> 1
A5: Bladder cancer | B5: No | C5: LIC | D5: begin | E5: 0 | F5: 0.05 | G5: =F5*dropdown!G$4 -> 0.045 | H5: =G5*dropdown!G$5 -> 0.0405 | I5: 0 | J5: 1 | K5: 0 | L5: 0 | M5: =SUM(I5:L5) -> 1
A6: Breast cancer | B6: No | C6: HIC | D6: begin | E6: 0.6 | F6: =E6*dropdown!G$3 -> 0.48 | G6: =F6*dropdown!G$4 -> 0.432 | H6: =G6*dropdown!G$5 -> 0.3888 | I6: 0 | J6: 0.5569338 | K6: 0.2467863 | L6: 0.1962798 | M6: =SUM(I6:L6) -> 0.9999999
A7: Breast cancer | B7: No | C7: UMIC | D7: begin | E7: 0.3 | F7: =E7*dropdown!G$3 -> 0.24 | G7: =F7*dropdown!G$4 -> 0.216 | H7: =G7*dropdown!G$5 -> 0.1944 | I7: 0 | J7: =E7 -> 0.3 | K7: 0.4 | L7: 0.3 | M7: =SUM(I7:L7) -> 1
A8: Breast cancer | B8: No | C8: LMIC | D8: begin | E8: 0.1 | F8: =E8*dropdown!G$3 -> 0.08 | G8: =F8*dropdown!G$4 -> 0.072 | H8: =G8*dropdown!G$5 -> 0.0648 | I8: 0 | J8: =E8 -> 0.1 | K8: 0.5 | L8: 0.4 | M8: =SUM(I8:L8) -> 1
A9: Breast cancer | B9: No | C9: LIC | D9: begin | E9: 0.05 | F9: =E9*dropdown!G$3 -> 0.04 | G9: =F9*dropdown!G$4 -> 0.036 | H9: =G9*dropdown!G$5 -> 0.0324 | I9: 0 | J9: =E9 -> 0.05 | K9: 0.35 | L9: 0.6 | M9: =SUM(I9:L9) -> 1
A10: Cervical cancer | B10: No | C10: HIC | D10: begin | E10: 0.77 | F10: =E10*dropdown!G$4 -> 0.693 | G10: =F10*dropdown!G$4 -> 0.6237 | H10: =G10*dropdown!G$5 -> 0.56133 | I10: 0.9 | J10: =49.50869% * (1-$I10) -> 0.04950869 | K10: =34.54271%*(1-$I10) -> 0.03454271 | L10: =15.948602%*(1-$I10) -> 0.015948602 | M10: =SUM(I10:L10) -> 1
A11: Cervical cancer | B11: No | C11: UMIC | D11: begin | E11: 0.43 | F11: =E11*dropdown!G$4 -> 0.387 | G11: =F11*dropdown!G$4 -> 0.3483 | H11: =G11*dropdown!G$5 -> 0.31347 | I11: =I10*(E11/E10) -> 0.5025974 | J11: =40% * (1-$I11) -> 0.19896104 | K11: =40%*(1-$I11) -> 0.19896104 | L11: =20%*(1-$I11) -> 0.099480519 | M11: =SUM(I11:L11) -> 1
A12: Cervical cancer | B12: No | C12: LMIC | D12: begin | E12: 0.07 | F12: =E12*dropdown!G$4 -> 0.063 | G12: =F12*dropdown!G$4 -> 0.0567 | H12: =G12*dropdown!G$5 -> 0.05103 | I12: =I10*(E12/E10) -> 0.081818182 | J12: =30% * (1-$I12) -> 0.27545455 | K12: =45%*(1-$I12) -> 0.41318182 | L12: =25%*(1-$I12) -> 0.22954545 | M12: =SUM(I12:L12) -> 1
A13: Cervical cancer | B13: No | C13: LIC | D13: begin | E13: 0.09 | F13: =E13*dropdown!G$4 -> 0.081 | G13: =F13*dropdown!G$4 -> 0.0729 | H13: =G13*dropdown!G$5 -> 0.06561 | I13: =I10*(E13/E10) -> 0.10519481 | J13: =20% * (1-$I13) -> 0.17896104 | K13: =50%*(1-$I13) -> 0.4474026 | L13: =30%*(1-$I13) -> 0.26844156 | M13: =SUM(I13:L13) -> 1
A14: Colon and rectum cancer | B14: No | C14: HIC | D14: begin | E14: 0.6 | F14: =E14*dropdown!G$4 -> 0.54 | G14: =F14*dropdown!G$4 -> 0.486 | H14: =G14*dropdown!G$5 -> 0.4374 | I14: 0.5 | J14: =37.69154%*(1-I14) -> 0.1884577 | K14: =40.03997%*(1-$I14) -> 0.20019985 | L14: =22.268488%*(1-I14) -> 0.11134244 | M14: =SUM(I14:L14) -> 0.99999999
A15: Colon and rectum cancer | B15: No | C15: UMIC | D15: begin | E15: 0.1 | F15: =E15*dropdown!G$4 -> 0.09 | G15: =F15*dropdown!G$4 -> 0.081 | H15: =G15*dropdown!G$5 -> 0.0729 | I15: =I14*(E15/E14) -> 0.083333333 | J15: =30%*(1-I15) -> 0.275 | K15: =45%*(1-$I15) -> 0.4125 | L15: =25%*(1-I15) -> 0.22916667 | M15: =SUM(I15:L15) -> 1
A16: Colon and rectum cancer | B16: No | C16: LMIC | D16: begin | E16: 0.05 | F16: =E16*dropdown!G$4 -> 0.045 | G16: =F16*dropdown!G$4 -> 0.0405 | H16: =G16*dropdown!G$5 -> 0.03645 | I16: =I15*(E16/E14) -> 0.0069444444 | J16: =25%*(1-I16) -> 0.24826389 | K16: =50%*(1-$I16) -> 0.49652778 | L16: =25%*(1-I16) -> 0.24826389 | M16: =SUM(I16:L16) -> 1
A17: Colon and rectum cancer | B17: No | C17: LIC | D17: begin | E17: 0.01 | F17: =E17*dropdown!G$4 -> 0.009 | G17: =F17*dropdown!G$4 -> 0.0081 | H17: =G17*dropdown!G$5 -> 0.00729 | I17: =I16*(E17/E14) -> 0.00011574074 | J17: =20%*(1-I17) -> 0.19997685 | K17: =55%*(1-$I17) -> 0.54993634 | L17: =25%*(1-I17) -> 0.24997106 | M17: =SUM(I17:L17) -> 1
A18: Esophageal cancer | B18: No | C18: HIC | D18: begin | E18: 0 | F18: 0.5 | G18: =F18*dropdown!G$4 -> 0.45 | H18: =G18*dropdown!G$5 -> 0.405 | I18: 0 | J18: 1 | K18: 0 | L18: 0 | M18: =SUM(I18:L18) -> 1
A19: Esophageal cancer | B19: No | C19: UMIC | D19: begin | E19: 0 | F19: 0.4 | G19: =F19*dropdown!G$4 -> 0.36 | H19: =G19*dropdown!G$5 -> 0.324 | I19: 0 | J19: 1 | K19: 0 | L19: 0 | M19: =SUM(I19:L19) -> 1
A20: Esophageal cancer | B20: No | C20: LMIC | D20: begin | E20: 0 | F20: 0.3 | G20: =F20*dropdown!G$4 -> 0.27 | H20: =G20*dropdown!G$5 -> 0.243 | I20: 0 | J20: 1 | K20: 0 | L20: 0 | M20: =SUM(I20:L20) -> 1
A21: Esophageal cancer | B21: No | C21: LIC | D21: begin | E21: 0 | F21: 0.05 | G21: =F21*dropdown!G$4 -> 0.045 | H21: =G21*dropdown!G$5 -> 0.0405 | I21: 0 | J21: 1 | K21: 0 | L21: 0 | M21: =SUM(I21:L21) -> 1
A22: Lip and oral cavity cancer | B22: No | C22: HIC | D22: begin | E22: 0 | F22: 0.5 | G22: =F22*dropdown!G$4 -> 0.45 | H22: =G22*dropdown!G$5 -> 0.405 | I22: 0 | J22: 1 | K22: 0 | L22: 0 | M22: =SUM(I22:L22) -> 1
A23: Lip and oral cavity cancer | B23: No | C23: UMIC | D23: begin | E23: 0 | F23: 0.4 | G23: =F23*dropdown!G$4 -> 0.36 | H23: =G23*dropdown!G$5 -> 0.324 | I23: 0 | J23: 1 | K23: 0 | L23: 0 | M23: =SUM(I23:L23) -> 1
A24: Lip and oral cavity cancer | B24: No | C24: LMIC | D24: begin | E24: 0 | F24: 0.3 | G24: =F24*dropdown!G$4 -> 0.27 | H24: =G24*dropdown!G$5 -> 0.243 | I24: 0 | J24: 1 | K24: 0 | L24: 0 | M24: =SUM(I24:L24) -> 1
A25: Lip and oral cavity cancer | B25: No | C25: LIC | D25: begin | E25: 0 | F25: 0.05 | G25: =F25*dropdown!G$4 -> 0.045 | H25: =G25*dropdown!G$5 -> 0.0405 | I25: 0 | J25: 1 | K25: 0 | L25: 0 | M25: =SUM(I25:L25) -> 1
A26: Liver cancer | B26: No | C26: HIC | D26: begin | E26: 0 | F26: 0.5 | G26: =F26*dropdown!G$4 -> 0.45 | H26: =G26*dropdown!G$5 -> 0.405 | I26: 0 | J26: 1 | K26: 0 | L26: 0 | M26: =SUM(I26:L26) -> 1
A27: Liver cancer | B27: No | C27: UMIC | D27: begin | E27: 0 | F27: 0.4 | G27: =F27*dropdown!G$4 -> 0.36 | H27: =G27*dropdown!G$5 -> 0.324 | I27: 0 | J27: 1 | K27: 0 | L27: 0 | M27: =SUM(I27:L27) -> 1
A28: Liver cancer | B28: No | C28: LMIC | D28: begin | E28: 0 | F28: 0.3 | G28: =F28*dropdown!G$4 -> 0.27 | H28: =G28*dropdown!G$5 -> 0.243 | I28: 0 | J28: 1 | K28: 0 | L28: 0 | M28: =SUM(I28:L28) -> 1
A29: Liver cancer | B29: No | C29: LIC | D29: begin | E29: 0 | F29: 0.05 | G29: =F29*dropdown!G$4 -> 0.045 | H29: =G29*dropdown!G$5 -> 0.0405 | I29: 0 | J29: 1 | K29: 0 | L29: 0 | M29: =SUM(I29:L29) -> 1
... A45: Pancreatic cancer | B45: No | C45: LIC | D45: begin | E45: 0 | F45: 0.05 | G45: =F45*dropdown!G$4 -> 0.045 | H45: =G45*dropdown!G$5 -> 0.0405 | I45: 0 | J45: 1 | K45: 0 | L45: 0 | M45: =SUM(I45:L45) -> 1
A46: Prostate cancer | B46: No | C46: HIC | D46: begin | E46: 0 | F46: 0.5 | G46: =F46*dropdown!G$4 -> 0.45 | H46: =G46*dropdown!G$5 -> 0.405 | I46: 0 | J46: 0.7455931 | K46: 0.1587829 | L46: =1-(J46+K46) -> 0.095624 | M46: =SUM(I46:L46) -> 1
A47: Prostate cancer | B47: No | C47: UMIC | D47: begin | E47: 0 | F47: 0.4 | G47: =F47*dropdown!G$4 -> 0.36 | H47: =G47*dropdown!G$5 -> 0.324 | I47: 0 | J47: =J46*(F47/F46) -> 0.59647448 | K47: =(1-J47)*K46/(K46+L46) -> 0.25185226 | L47: =1-(J47+K47) -> 0.15167326 | M47: =SUM(I47:L47) -> 1
A48: Prostate cancer | B48: No | C48: LMIC | D48: begin | E48: 0 | F48: 0.3 | G48: =F48*dropdown!G$4 -> 0.27 | H48: =G48*dropdown!G$5 -> 0.243 | I48: 0 | J48: =J47*(F48/F46) -> 0.35788469 | K48: =(1-J48)*K47/(K47+L47) -> 0.40076323 | L48: =1-(J48+K48) -> 0.24135208 | M48: =SUM(I48:L48) -> 1
A49: Prostate cancer | B49: No | C49: LIC | D49: begin | E49: 0 | F49: 0.05 | G49: =F49*dropdown!G$4 -> 0.045 | H49: =G49*dropdown!G$5 -> 0.0405 | I49: 0 | J49: =J48*(F49/F46) -> 0.035788469 | K49: =(1-J49)*K48/(K48+L48) -> 0.60179305 | L49: =1-(J49+K49) -> 0.36241849 | M49: =SUM(I49:L49) -> 1
A50: Stomach cancer | B50: No | C50: HIC | D50: begin | E50: 0 | F50: 0.5 | G50: =F50*dropdown!G$4 -> 0.45 | H50: =G50*dropdown!G$5 -> 0.405 | I50: 0 | J50: 1 | K50: 0 | L50: 0 | M50: =SUM(I50:L50) -> 1
A51: Stomach cancer | B51: No | C51: UMIC | D51: begin | E51: 0 | F51: 0.4 | G51: =F51*dropdown!G$4 -> 0.36 | H51: =G51*dropdown!G$5 -> 0.324 | I51: 0 | J51: 1 | K51: 0 | L51: 0 | M51: =SUM(I51:L51) -> 1
A52: Stomach cancer | B52: No | C52: LMIC | D52: begin | E52: 0 | F52: 0.3 | G52: =F52*dropdown!G$4 -> 0.27 | H52: =G52*dropdown!G$5 -> 0.243 | I52: 0 | J52: 1 | K52: 0 | L52: 0 | M52: =SUM(I52:L52) -> 1
A53: Stomach cancer | B53: No | C53: LIC | D53: begin | E53: 0 | F53: 0.05 | G53: =F53*dropdown!G$4 -> 0.045 | H53: =G53*dropdown!G$5 -> 0.0405 | I53: 0 | J53: 1 | K53: 0 | L53: 0 | M53: =SUM(I53:L53) -> 1
A54: Thyroid cancer | B54: No | C54: HIC | D54: begin | E54: 0 | F54: 0.5 | G54: =F54*dropdown!G$4 -> 0.45 | H54: =G54*dropdown!G$5 -> 0.405 | I54: 0 | J54: 1 | K54: 0 | L54: 0 | M54: =SUM(I54:L54) -> 1
A55: Thyroid cancer | B55: No | C55: UMIC | D55: begin | E55: 0 | F55: 0.4 | G55: =F55*dropdown!G$4 -> 0.36 | H55: =G55*dropdown!G$5 -> 0.324 | I55: 0 | J55: 1 | K55: 0 | L55: 0 | M55: =SUM(I55:L55) -> 1
A56: Thyroid cancer | B56: No | C56: LMIC | D56: begin | E56: 0 | F56: 0.3 | G56: =F56*dropdown!G$4 -> 0.27 | H56: =G56*dropdown!G$5 -> 0.243 | I56: 0 | J56: 1 | K56: 0 | L56: 0 | M56: =SUM(I56:L56) -> 1
A57: Thyroid cancer | B57: No | C57: LIC | D57: begin | E57: 0 | F57: 0.05 | G57: =F57*dropdown!G$4 -> 0.045 | H57: =G57*dropdown!G$5 -> 0.0405 | I57: 0 | J57: 1 | K57: 0 | L57: 0 | M57: =SUM(I57:L57) -> 1
A58: Tracheal, bronchus, and lung cancer | B58: No | C58: HIC | D58: begin | E58: 0 | F58: 0.5 | G58: =F58*dropdown!G$4 -> 0.45 | H58: =G58*dropdown!G$5 -> 0.405 | I58: 0 | J58: 0.2671015 | K58: 0.2118995 | L58: 0.52099905 | M58: =SUM(I58:L58) -> 1.0000001
A59: Tracheal, bronchus, and lung cancer | B59: No | C59: UMIC | D59: begin | E59: 0 | F59: 0.4 | G59: =F59*dropdown!G$4 -> 0.36 | H59: =G59*dropdown!G$5 -> 0.324 | I59: 0 | J59: 0.2 | K59: 0.2 | L59: 0.6 | M59: =SUM(I59:L59) -> 1
A60: Tracheal, bronchus, and lung cancer | B60: No | C60: LMIC | D60: begin | E60: 0 | F60: 0.3 | G60: =F60*dropdown!G$4 -> 0.27 | H60: =G60*dropdown!G$5 -> 0.243 | I60: 0 | J60: 0.15 | K60: 0.15 | L60: 0.7 | M60: =SUM(I60:L60) -> 1
A61: Tracheal, bronchus, and lung cancer | B61: No | C61: LIC | D61: begin | E61: 0 | F61: 0.05 | G61: =F61*dropdown!G$4 -> 0.045 | H61: =G61*dropdown!G$5 -> 0.0405 | I61: 0 | J61: 0.05 | K61: 0.15 | L61: 0.8 | M61: =SUM(I61:L61) -> 1
... A65: Uterine cancer | B65: No | C65: LIC | D65: begin | E65: 0 | F65: 0.05 | G65: =F65*dropdown!G$4 -> 0.045 | H65: =G65*dropdown!G$5 -> 0.0405 | I65: 0 | J65: 1 | K65: 0 | L65: 0 | M65: =SUM(I65:L65) -> 1

Sheet end
A1: cause | B1: Intervention | C1: Setting | D1: Scaleup | E1: Screened | F1: Diagnosed | G1: Treated | H1: Completed | I1: Precancer | J1: Local | K1: Regional | L1: Distant | M1: Total
A2: Bladder cancer | B2: Yes | C2: HIC | D2: end | E2: 0 | F2: 0.8 | G2: =F2*dropdown!G$4 -> 0.72 | H2: =G2*dropdown!G$5 -> 0.648 | I2: 0 | J2: 1 | K2: 0 | L2: 0 | M2: =SUM(I2:L2) -> 1
A3: Bladder cancer | B3: Yes | C3: UMIC | D3: end | E3: 0 | F3: 0.8 | G3: =F3*dropdown!G$4 -> 0.72 | H3: =G3*dropdown!G$5 -> 0.648 | I3: 0 | J3: 1 | K3: 0 | L3: 0 | M3: =SUM(I3:L3) -> 1
A4: Bladder cancer | B4: Yes | C4: LMIC | D4: end | E4: 0 | F4: 0.8 | G4: =F4*dropdown!G$4 -> 0.72 | H4: =G4*dropdown!G$5 -> 0.648 | I4: 0 | J4: 1 | K4: 0 | L4: 0 | M4: =SUM(I4:L4) -> 1
A5: Bladder cancer | B5: Yes | C5: LIC | D5: end | E5: 0 | F5: 0.8 | G5: =F5*dropdown!G$4 -> 0.72 | H5: =G5*dropdown!G$5 -> 0.648 | I5: 0 | J5: 1 | K5: 0 | L5: 0 | M5: =SUM(I5:L5) -> 1
A6: Breast cancer | B6: Yes | C6: HIC | D6: end | E6: =dropdown!G$2 -> 0.8 | F6: =E6*dropdown!G$4 -> 0.72 | G6: =F6*dropdown!G$4 -> 0.648 | H6: =G6*dropdown!G$5 -> 0.5832
A7: Breast cancer | B7: Yes | C7: UMIC | D7: end | E7: =dropdown!G$2 -> 0.8 | F7: =E7*dropdown!G$4 -> 0.72 | G7: =F7*dropdown!G$4 -> 0.648 | H7: =G7*dropdown!G$5 -> 0.5832
A8: Breast cancer | B8: Yes | C8: LMIC | D8: end | E8: =dropdown!G$2 -> 0.8 | F8: =E8*dropdown!G$4 -> 0.72 | G8: =F8*dropdown!G$4 -> 0.648 | H8: =G8*dropdown!G$5 -> 0.5832
A9: Breast cancer | B9: Yes | C9: LIC | D9: end | E9: =dropdown!G$2 -> 0.8 | F9: =E9*dropdown!G$4 -> 0.72 | G9: =F9*dropdown!G$4 -> 0.648 | H9: =G9*dropdown!G$5 -> 0.5832
A10: Cervical cancer | B10: Yes | C10: HIC | D10: end | E10: =dropdown!G$2 -> 0.8 | F10: =E10*dropdown!G$4 -> 0.72 | G10: =F10*dropdown!G$4 -> 0.648 | H10: =G10*dropdown!G$5 -> 0.5832
A11: Cervical cancer | B11: Yes | C11: UMIC | D11: end | E11: =dropdown!G$2 -> 0.8 | F11: =E11*dropdown!G$4 -> 0.72 | G11: =F11*dropdown!G$4 -> 0.648 | H11: =G11*dropdown!G$5 -> 0.5832
A12: Cervical cancer | B12: Yes | C12: LMIC | D12: end | E12: =dropdown!G$2 -> 0.8 | F12: =E12*dropdown!G$4 -> 0.72 | G12: =F12*dropdown!G$4 -> 0.648 | H12: =G12*dropdown!G$5 -> 0.5832
A13: Cervical cancer | B13: Yes | C13: LIC | D13: end | E13: =dropdown!G$2 -> 0.8 | F13: =E13*dropdown!G$4 -> 0.72 | G13: =F13*dropdown!G$4 -> 0.648 | H13: =G13*dropdown!G$5 -> 0.5832
A14: Colon and rectum cancer | B14: Yes | C14: HIC | D14: end | E14: =dropdown!G$2 -> 0.8 | F14: =E14*dropdown!G$4 -> 0.72 | G14: =F14*dropdown!G$4 -> 0.648 | H14: =G14*dropdown!G$5 -> 0.5832
A15: Colon and rectum cancer | B15: Yes | C15: UMIC | D15: end | E15: =dropdown!G$2 -> 0.8 | F15: =E15*dropdown!G$4 -> 0.72 | G15: =F15*dropdown!G$4 -> 0.648 | H15: =G15*dropdown!G$5 -> 0.5832
A16: Colon and rectum cancer | B16: Yes | C16: LMIC | D16: end | E16: =dropdown!G$2 -> 0.8 | F16: =E16*dropdown!G$4 -> 0.72 | G16: =F16*dropdown!G$4 -> 0.648 | H16: =G16*dropdown!G$5 -> 0.5832
A17: Colon and rectum cancer | B17: Yes | C17: LIC | D17: end | E17: =dropdown!G$2 -> 0.8 | F17: =E17*dropdown!G$4 -> 0.72 | G17: =F17*dropdown!G$4 -> 0.648 | H17: =G17*dropdown!G$5 -> 0.5832
A18: Esophageal cancer | B18: Yes | C18: HIC | D18: end | E18: 0 | F18: 0.8 | G18: =F18*dropdown!G$4 -> 0.72 | H18: =G18*dropdown!G$5 -> 0.648 | I18: 0 | J18: 1 | K18: 0 | L18: 0 | M18: =SUM(I18:L18) -> 1
A19: Esophageal cancer | B19: Yes | C19: UMIC | D19: end | E19: 0 | F19: 0.8 | G19: =F19*dropdown!G$4 -> 0.72 | H19: =G19*dropdown!G$5 -> 0.648 | I19: 0 | J19: 1 | K19: 0 | L19: 0 | M19: =SUM(I19:L19) -> 1
A20: Esophageal cancer | B20: Yes | C20: LMIC | D20: end | E20: 0 | F20: 0.8 | G20: =F20*dropdown!G$4 -> 0.72 | H20: =G20*dropdown!G$5 -> 0.648 | I20: 0 | J20: 1 | K20: 0 | L20: 0 | M20: =SUM(I20:L20) -> 1
A21: Esophageal cancer | B21: Yes | C21: LIC | D21: end | E21: 0 | F21: 0.8 | G21: =F21*dropdown!G$4 -> 0.72 | H21: =G21*dropdown!G$5 -> 0.648 | I21: 0 | J21: 1 | K21: 0 | L21: 0 | M21: =SUM(I21:L21) -> 1
A22: Lip and oral cavity cancer | B22: Yes | C22: HIC | D22: end | E22: 0 | F22: 0.8 | G22: =F22*dropdown!G$4 -> 0.72 | H22: =G22*dropdown!G$5 -> 0.648 | I22: 0 | J22: 1 | K22: 0 | L22: 0 | M22: =SUM(I22:L22) -> 1
A23: Lip and oral cavity cancer | B23: Yes | C23: UMIC | D23: end | E23: 0 | F23: 0.8 | G23: =F23*dropdown!G$4 -> 0.72 | H23: =G23*dropdown!G$5 -> 0.648 | I23: 0 | J23: 1 | K23: 0 | L23: 0 | M23: =SUM(I23:L23) -> 1
A24: Lip and oral cavity cancer | B24: Yes | C24: LMIC | D24: end | E24: 0 | F24: 0.8 | G24: =F24*dropdown!G$4 -> 0.72 | H24: =G24*dropdown!G$5 -> 0.648 | I24: 0 | J24: 1 | K24: 0 | L24: 0 | M24: =SUM(I24:L24) -> 1
A25: Lip and oral cavity cancer | B25: Yes | C25: LIC | D25: end | E25: 0 | F25: 0.8 | G25: =F25*dropdown!G$4 -> 0.72 | H25: =G25*dropdown!G$5 -> 0.648 | I25: 0 | J25: 1 | K25: 0 | L25: 0 | M25: =SUM(I25:L25) -> 1
A26: Liver cancer | B26: Yes | C26: HIC | D26: end | E26: 0 | F26: 0.8 | G26: =F26*dropdown!G$4 -> 0.72 | H26: =G26*dropdown!G$5 -> 0.648 | I26: 0 | J26: 1 | K26: 0 | L26: 0 | M26: =SUM(I26:L26) -> 1
A27: Liver cancer | B27: Yes | C27: UMIC | D27: end | E27: 0 | F27: 0.8 | G27: =F27*dropdown!G$4 -> 0.72 | H27: =G27*dropdown!G$5 -> 0.648 | I27: 0 | J27: 1 | K27: 0 | L27: 0 | M27: =SUM(I27:L27) -> 1
A28: Liver cancer | B28: Yes | C28: LMIC | D28: end | E28: 0 | F28: 0.8 | G28: =F28*dropdown!G$4 -> 0.72 | H28: =G28*dropdown!G$5 -> 0.648 | I28: 0 | J28: 1 | K28: 0 | L28: 0 | M28: =SUM(I28:L28) -> 1
A29: Liver cancer | B29: Yes | C29: LIC | D29: end | E29: 0 | F29: 0.8 | G29: =F29*dropdown!G$4 -> 0.72 | H29: =G29*dropdown!G$5 -> 0.648 | I29: 0 | J29: 1 | K29: 0 | L29: 0 | M29: =SUM(I29:L29) -> 1
... A45: Pancreatic cancer | B45: Yes | C45: LIC | D45: end | E45: 0 | F45: 0.8 | G45: =F45*dropdown!G$4 -> 0.72 | H45: =G45*dropdown!G$5 -> 0.648 | I45: 0 | J45: 1 | K45: 0 | L45: 0 | M45: =SUM(I45:L45) -> 1
A46: Prostate cancer | B46: Yes | C46: HIC | D46: end | E46: 0 | F46: =dropdown!G$3 -> 0.8 | G46: =F46*dropdown!G$4 -> 0.72 | H46: =G46*dropdown!G$5 -> 0.648 | I46: 0 | J46: 0.7455931 | K46: 0.1587829 | L46: 0.095624 | M46: =SUM(I46:L46) -> 1
A47: Prostate cancer | B47: Yes | C47: UMIC | D47: end | E47: 0 | F47: =dropdown!G$3 -> 0.8 | G47: =F47*dropdown!G$4 -> 0.72 | H47: =G47*dropdown!G$5 -> 0.648 | I47: 0 | J47: 0.59647448 | K47: 0.25185226 | L47: 0.15167326 | M47: =SUM(I47:L47) -> 1
A48: Prostate cancer | B48: Yes | C48: LMIC | D48: end | E48: 0 | F48: =dropdown!G$3 -> 0.8 | G48: =F48*dropdown!G$4 -> 0.72 | H48: =G48*dropdown!G$5 -> 0.648 | I48: 0 | J48: 0.35788469 | K48: 0.40076323 | L48: 0.24135208 | M48: =SUM(I48:L48) -> 1
A49: Prostate cancer | B49: Yes | C49: LIC | D49: end | E49: 0 | F49: =dropdown!G$3 -> 0.8 | G49: =F49*dropdown!G$4 -> 0.72 | H49: =G49*dropdown!G$5 -> 0.648 | I49: 0 | J49: 0.035788469 | K49: 0.60179305 | L49: 0.36241849 | M49: =SUM(I49:L49) -> 1
A50: Stomach cancer | B50: Yes | C50: HIC | D50: end | E50: 0 | F50: 0.8 | G50: =F50*dropdown!G$4 -> 0.72 | H50: =G50*dropdown!G$5 -> 0.648 | I50: 0 | J50: 1 | K50: 0 | L50: 0 | M50: =SUM(I50:L50) -> 1
A51: Stomach cancer | B51: Yes | C51: UMIC | D51: end | E51: 0 | F51: 0.8 | G51: =F51*dropdown!G$4 -> 0.72 | H51: =G51*dropdown!G$5 -> 0.648 | I51: 0 | J51: 1 | K51: 0 | L51: 0 | M51: =SUM(I51:L51) -> 1
A52: Stomach cancer | B52: Yes | C52: LMIC | D52: end | E52: 0 | F52: 0.8 | G52: =F52*dropdown!G$4 -> 0.72 | H52: =G52*dropdown!G$5 -> 0.648 | I52: 0 | J52: 1 | K52: 0 | L52: 0 | M52: =SUM(I52:L52) -> 1
A53: Stomach cancer | B53: Yes | C53: LIC | D53: end | E53: 0 | F53: 0.8 | G53: =F53*dropdown!G$4 -> 0.72 | H53: =G53*dropdown!G$5 -> 0.648 | I53: 0 | J53: 1 | K53: 0 | L53: 0 | M53: =SUM(I53:L53) -> 1
A54: Thyroid cancer | B54: Yes | C54: HIC | D54: end | E54: 0 | F54: 0.8 | G54: =F54*dropdown!G$4 -> 0.72 | H54: =G54*dropdown!G$5 -> 0.648 | I54: 0 | J54: 1 | K54: 0 | L54: 0 | M54: =SUM(I54:L54) -> 1
A55: Thyroid cancer | B55: Yes | C55: UMIC | D55: end | E55: 0 | F55: 0.8 | G55: =F55*dropdown!G$4 -> 0.72 | H55: =G55*dropdown!G$5 -> 0.648 | I55: 0 | J55: 1 | K55: 0 | L55: 0 | M55: =SUM(I55:L55) -> 1
A56: Thyroid cancer | B56: Yes | C56: LMIC | D56: end | E56: 0 | F56: 0.8 | G56: =F56*dropdown!G$4 -> 0.72 | H56: =G56*dropdown!G$5 -> 0.648 | I56: 0 | J56: 1 | K56: 0 | L56: 0 | M56: =SUM(I56:L56) -> 1
A57: Thyroid cancer | B57: Yes | C57: LIC | D57: end | E57: 0 | F57: 0.8 | G57: =F57*dropdown!G$4 -> 0.72 | H57: =G57*dropdown!G$5 -> 0.648 | I57: 0 | J57: 1 | K57: 0 | L57: 0 | M57: =SUM(I57:L57) -> 1
A58: Tracheal, bronchus, and lung cancer | B58: Yes | C58: HIC | D58: end | E58: 0 | F58: =dropdown!G$3 -> 0.8 | G58: =F58*dropdown!G$4 -> 0.72 | H58: =G58*dropdown!G$5 -> 0.648 | I58: 0 | J58: 0.2671015 | K58: 0.2118995 | L58: 0.52099905
A59: Tracheal, bronchus, and lung cancer | B59: Yes | C59: UMIC | D59: end | E59: 0 | F59: =dropdown!G$3 -> 0.8 | G59: =F59*dropdown!G$4 -> 0.72 | H59: =G59*dropdown!G$5 -> 0.648 | I59: 0 | J59: 0.2 | K59: 0.2 | L59: 0.6
A60: Tracheal, bronchus, and lung cancer | B60: Yes | C60: LMIC | D60: end | E60: 0 | F60: =dropdown!G$3 -> 0.8 | G60: =F60*dropdown!G$4 -> 0.72 | H60: =G60*dropdown!G$5 -> 0.648 | I60: 0 | J60: 0.15 | K60: 0.15 | L60: 0.7
A61: Tracheal, bronchus, and lung cancer | B61: Yes | C61: LIC | D61: end | E61: 0 | F61: =dropdown!G$3 -> 0.8 | G61: =F61*dropdown!G$4 -> 0.72 | H61: =G61*dropdown!G$5 -> 0.648 | I61: 0 | J61: 0.05 | K61: 0.15 | L61: 0.8
A62: Uterine cancer | B62: Yes | C62: HIC | D62: end | E62: 0 | F62: 0.8 | G62: =F62*dropdown!G$4 -> 0.72 | H62: =G62*dropdown!G$5 -> 0.648 | I62: 0 | J62: 1 | K62: 0 | L62: 0 | M62: =SUM(I62:L62) -> 1
A63: Uterine cancer | B63: Yes | C63: UMIC | D63: end | E63: 0 | F63: 0.8 | G63: =F63*dropdown!G$4 -> 0.72 | H63: =G63*dropdown!G$5 -> 0.648 | I63: 0 | J63: 1 | K63: 0 | L63: 0 | M63: =SUM(I63:L63) -> 1
A64: Uterine cancer | B64: Yes | C64: LMIC | D64: end | E64: 0 | F64: 0.8 | G64: =F64*dropdown!G$4 -> 0.72 | H64: =G64*dropdown!G$5 -> 0.648 | I64: 0 | J64: 1 | K64: 0 | L64: 0 | M64: =SUM(I64:L64) -> 1
A65: Uterine cancer | B65: Yes | C65: LIC | D65: end | E65: 0 | F65: 0.8 | G65: =F65*dropdown!G$4 -> 0.72 | H65: =G65*dropdown!G$5 -> 0.648 | I65: 0 | J65: 1 | K65: 0 | L65: 0 | M65: =SUM(I65:L65) -> 1
